Workbook

Sheet DATA
A1: Proyecto | B1: Asesor | C1: N° | D1: Días Hábiles | E1: Periodo | F1: Desde | G1: Hasta | H1: Adelanto $ | I1: Negocios | J1: Departamentos a visitar | K1: Auto | L1: Costo Vehículo USD | M1: diferencia a pagar | N1: Boletas presentadas | O1: Negocios a Menos 100 KM (con o sin actividad) | P1: Negocios a Más de 100 KM (con o sin actividad) | Q1: Total Negocios | R1: Costo por negocio | S1: Cuenta Corriente | T1: Fecha Rendicion | U1: Tiempo | V1: Forma | W1: Detalle CI | X1: Observaciones de T y F | Y1: Matricula | Z1: Control de entrega a adm. | AA1: Factura | AB1: Fecha de Pago | AC1: Monto Factura | AD1: incial Km | AE1: incial fecha y hora | AF1: final Km | AG1: final fecha y hora | AH1: Km totales | AI1: Dias | AJ1: Negocios esperados | AK1: Diferencia | AM1: km * Afiliacion ida y vuelta | AN1: Afiliaciones * día | AO1: Criterio 11 km p/litro Max $ teorico | AP1: A favor + o negativo gasto mas de lo teorico | AQ1: Litros rendidos | AR1: Litros teoricos | AS1: Litros teoricos menos reales | AT1: Rendimiento real | AU1: Salida Gabriela con Asesor 1 | AV1: Salida Gabriela con Asesor 2 | AW1: Salida Gabriela con Asesor 3 | AX1: Salida Gabriela con Asesor 4 | AY1: Proyecto de Gabriela?
A2: 1 | B2: Ignacio Ceroni | C2: 3007 | D2: 4 | E2: 05/01 al 08/01/2026 | F2: 46027 | G2: 46030 | H2: 5000 | I2: 15 | J2: Montevideo, Maldonado | K2: Alquiler | M2: =+N2-H2 -> 58.9 | N2: =2458.9+2000+600 -> 5058.9 | P2: =20+6 -> 26 | Q2: =+P2+O2 -> 26 | R2: =(N2/Q2) -> 194.57308 | S2: =(('Costo por negocio'!$B$2-DATA!R2)*DATA!O2)+('Costo por negocio'!$C$2-DATA!R2)*DATA!P2 -> 5133.1 | T2: 46031 | U2: SI | V2: SI | W2: SI | Y2: BEC 5478 | AA2: 94621 | AC2: 148 | AD2: 72534 | AE2: 46027.375 | AF2: 73864 | AG2: 46031.389 | AH2: =+AF2-AD2 -> 1330 | AI2: 3 | AJ2: =+AI2*5 -> 15 | AK2: =+Q2-AJ2 -> 11 | AM2: =+AH2/Q2 -> 51.153846 | AN2: =+Q2/AI2 -> 8.6666667 | AQ2: =+N2/78.54 -> 64.411765 | AR2: =+AH2/11 -> 120.90909 | AS2: =+AR2-AQ2 -> 56.497326 | AT2: =+AH2/AQ2 -> 20.648402
A3: 2 | B3: Claudia Parrilla | C3: 2005 | D3: 3 | E3: 07/01 al 09/01/2026 | F3: 46029 | G3: 46031 | H3: 5000 | I3: 15 | J3: Montevideo, San José | K3: Alquiler | M3: =+N3-H3 -> -930.3 | N3: 4069.7 | O3: 7 | P3: 9 | Q3: =+P3+O3 -> 16 | R3: =(N3/Q3) -> 254.35625 | S3: =(('Costo por negocio'!$B$2-DATA!R3)*DATA!O3)+('Costo por negocio'!$C$2-DATA!R3)*DATA!P3 -> 1299.3 | T3: 46034 | U3: SI | V3: SI | W3: SI | Y3: BEB 1766 | AA3: 94630 | AC3: 111 | AD3: 121499 | AE3: 46029.398 | AF3: 122071 | AG3: 46032.376 | AH3: =+AF3-AD3 -> 572 | AI3: 3 | AJ3: =+AI3*5 -> 15 | AK3: =+Q3-AJ3 -> 1 | AM3: =+AH3/Q3 -> 35.75 | AN3: =+Q3/AI3 -> 5.3333333 | AQ3: =+N3/78.54 -> 51.816909 | AR3: =+AH3/11 -> 52 | AS3: =+AR3-AQ3 -> 0.18309142 | AT3: =+AH3/AQ3 -> 11.038868
A4: 3 | B4: Natalia Greco | C4: 3154 | D4: 3 | E4: 07/01 al 09/01/2026 | F4: 46029 | G4: 46031 | H4: 5000 | I4: 15 | J4: Montevideo, Lavalleja | K4: Alquiler | M4: =+N4-H4 -> -2333 | N4: =1500+1167 -> 2667 | P4: =8+7 -> 15 | Q4: =+P4+O4 -> 15 | R4: =(N4/Q4) -> 177.8 | S4: =(('Costo por negocio'!$B$2-DATA!R4)*DATA!O4)+('Costo por negocio'!$C$2-DATA!R4)*DATA!P4 -> 3213 | T4: 46034 | U4: SI | V4: SI | W4: SI | Y4: BEC 5664 | AA4: 94624 | AC4: 111 | AD4: 68806 | AE4: 46029.375 | AF4: 69300 | AG4: 46031.506 | AH4: =+AF4-AD4 -> 494 | AI4: 2 | AJ4: =+AI4*5 -> 10 | AK4: =+Q4-AJ4 -> 5 | AM4: =+AH4/Q4 -> 32.933333 | AN4: =+Q4/AI4 -> 7.5 | AQ4: =+N4/78.54 -> 33.957219 | AR4: =+AH4/11 -> 44.909091 | AS4: =+AR4-AQ4 -> 10.951872 | AT4: =+AH4/AQ4 -> 14.547717
A5: 4 | B5: Lorena Cabrera | C5: 1618 | D5: 3 | E5: 07/01 al 09/01/2026 | F5: 46029 | G5: 46031 | H5: 4000 | I5: 15 | J5: Canelones, Maldonado | K5: Alquiler | M5: =+N5-H5 -> -2125.5 | N5: 1874.5 | O5: 5 | Q5: =+P5+O5 -> 5 | R5: =(N5/Q5) -> 374.9 | S5: =(('Costo por negocio'!$B$2-DATA!R5)*DATA!O5)+('Costo por negocio'!$C$2-DATA!R5)*DATA!P5 -> -559.5 | T5: 46038 | U5: SI | V5: SI | W5: SI | Y5: BEB 2357 | AA5: 93044 | AC5: 111 | AD5: 134524 | AE5: 46029.375 | AF5: 134856 | AG5: 46032.375 | AH5: =+AF5-AD5 -> 332 | AI5: 3 | AJ5: =+AI5*5 -> 15 | AK5: =+Q5-AJ5 -> -10 | AM5: =+AH5/Q5 -> 66.4 | AN5: =+Q5/AI5 -> 1.6666667 | AQ5: =+N5/78.54 -> 23.866819 | AR5: =+AH5/11 -> 30.181818 | AS5: =+AR5-AQ5 -> 6.3149987 | AT5: =+AH5/AQ5 -> 13.910525
A6: 5 | B6: Ricardo Cardona | C6: 1512 | D6: 2 | E6: 07/01 al 08/01/2026 | F6: 46029 | G6: 46030 | H6: 6000 | I6: 10 | J6: Flores, Durazno | K6: Alquiler | M6: =+N6-H6 -> -2101.5 | N6: =2098+1000.5+800 -> 3898.5 | P6: 8 | Q6: =+P6+O6 -> 8 | R6: =(N6/Q6) -> 487.3125 | S6: =(('Costo por negocio'!$B$2-DATA!R6)*DATA!O6)+('Costo por negocio'!$C$2-DATA!R6)*DATA!P6 -> -762.5 | T6: 46031 | U6: SI | V6: SI | W6: SI | Y6: BEC 5528 | AA6: 94619 | AC6: 74 | AD6: 80882 | AE6: 46029.399 | AF6: 81499 | AG6: 46031.377 | AH6: =+AF6-AD6 -> 617 | AI6: 2 | AJ6: =+AI6*5 -> 10 | AK6: =+Q6-AJ6 -> -2 | AM6: =+AH6/Q6 -> 77.125 | AN6: =+Q6/AI6 -> 4 | AQ6: =+N6/78.54 -> 49.637128 | AR6: =+AH6/11 -> 56.090909 | AS6: =+AR6-AQ6 -> 6.4537815 | AT6: =+AH6/AQ6 -> 12.430212
A7: 6 | B7: Luis Amicone | C7: 3075 | D7: 3 | E7: 07/01 al 09/01/2026 | F7: 46029 | G7: 46031 | H7: 7000 | I7: 15 | J7: Montevideo, Treinta y Tres | K7: Alquiler | M7: =+N7-H7 -> -1984.9 | N7: =3020.1+1995 -> 5015.1 | P7: 20 | Q7: =+P7+O7 -> 20 | R7: =(N7/Q7) -> 250.755 | S7: =(('Costo por negocio'!$B$2-DATA!R7)*DATA!O7)+('Costo por negocio'!$C$2-DATA!R7)*DATA!P7 -> 2824.9 | T7: 46031 | U7: SI | V7: SI | W7: SI | Y7: BAA 7043 | AA7: 94618 | AC7: 74 | AD7: 108671 | AE7: 46029.42 | AF7: 109436 | AG7: 46031.378 | AH7: =+AF7-AD7 -> 765 | AI7: 2 | AJ7: =+AI7*5 -> 10 | AK7: =+Q7-AJ7 -> 10 | AM7: =+AH7/Q7 -> 38.25 | AN7: =+Q7/AI7 -> 10 | AQ7: =+N7/78.54 -> 63.854087 | AR7: =+AH7/11 -> 69.545455 | AS7: =+AR7-AQ7 -> 5.6913675 | AT7: =+AH7/AQ7 -> 11.980439
A8: 7 | B8: Ricardo Cardona | C8: 1512 | D8: 3 | E8: 13/01 al 15/01/2026 | F8: 46035 | G8: 46037 | H8: 7000 | I8: 15 | J8: Canelones, Maldonado | K8: Alquiler | M8: =+N8-H8 -> -2020.1 | N8: =2158.9+1406.8+1414.2 -> 4979.9 | P8: =3+3 -> 6 | Q8: =+P8+O8 -> 6 | R8: =(N8/Q8) -> 829.98333 | S8: =(('Costo por negocio'!$B$2-DATA!R8)*DATA!O8)+('Costo por negocio'!$C$2-DATA!R8)*DATA!P8 -> -2627.9 | T8: 46038 | U8: SI | V8: SI | W8: SI | Y8: BGC 5535 | AA8: 94661 | AC8: 148 | AD8: 65254 | AE8: 46034.684 | AF8: 66076 | AG8: 46038.384 | AH8: =+AF8-AD8 -> 822 | AI8: 3 | AJ8: =+AI8*5 -> 15 | AK8: =+Q8-AJ8 -> -9 | AM8: =+AH8/Q8 -> 137 | AN8: =+Q8/AI8 -> 2 | AQ8: =+N8/78.54 -> 63.405908 | AR8: =+AH8/11 -> 74.727273 | AS8: =+AR8-AQ8 -> 11.321365 | AT8: =+AH8/AQ8 -> 12.964092
A9: 8 | B9: Ignacio Ceroni | C9: 3007 | D9: 4 | E9: 12/01 al 15/01/2026 | F9: 46034 | G9: 46037 | H9: 4000 | I9: =5*4 -> 20 | J9: Montevideo, Maldonado | K9: Alquiler | M9: =+N9-H9 -> 405 | N9: =3005+1400 -> 4405 | O9: =11+10 -> 21 | P9: 9 | Q9: =+P9+O9 -> 30 | R9: =(N9/Q9) -> 146.83333 | S9: =(('Costo por negocio'!$B$2-DATA!R9)*DATA!O9)+('Costo por negocio'!$C$2-DATA!R9)*DATA!P9 -> 4646 | T9: 46038 | U9: SI | V9: SI | W9: SI | Y9: BEC 5472 | AA9: 94662 | AC9: 148 | AD9: 81576 | AE9: 46034.375 | AF9: 82324 | AG9: 46038.375 | AH9: =+AF9-AD9 -> 748 | AI9: 4 | AJ9: =+AI9*5 -> 20 | AK9: =+Q9-AJ9 -> 10 | AM9: =+AH9/Q9 -> 24.933333 | AN9: =+Q9/AI9 -> 7.5 | AQ9: =+N9/78.54 -> 56.086071 | AR9: =+AH9/11 -> 68 | AS9: =+AR9-AQ9 -> 11.913929 | AT9: =+AH9/AQ9 -> 13.336645
A10: 9 | B10: Claudia Parrilla | C10: 2005 | D10: 3 | E10: 13/01 al 15/01/2026 | F10: 46035 | G10: 46037 | H10: =18*263 -> 4734 | I10: 15 | J10: Montevideo, Canelones | K10: Alquiler | M10: =+N10-H10 -> -915.1 | N10: =2318.9+1500 -> 3818.9 | O10: 10 | P10: 7 | Q10: =+P10+O10 -> 17 | R10: =(N10/Q10) -> 224.64118 | S10: =(('Costo por negocio'!$B$2-DATA!R10)*DATA!O10)+('Costo por negocio'!$C$2-DATA!R10)*DATA!P10 -> 1555.1 | T10: 46038 | U10: SI | V10: SI | W10: SI | Y10: BEC 5634 | AA10: 94659 | AC10: 111 | AD10: 78912 | AE10: 46035.382 | AF10: 79558 | AG10: 46038.376 | AH10: =+AF10-AD10 -> 646 | AI10: 3 | AJ10: =+AI10*5 -> 15 | AK10: =+Q10-AJ10 -> 2 | AM10: =+AH10/Q10 -> 38 | AN10: =+Q10/AI10 -> 5.6666667 | AQ10: =+N10/78.54 -> 48.623631 | AR10: =+AH10/11 -> 58.727273 | AS10: =+AR10-AQ10 -> 10.103641 | AT10: =+AH10/AQ10 -> 13.285721
A11: 10 | B11: Luis Amicone | C11: 3075 | D11: 3 | E11: 13/01 al 15/01/2026 | F11: 46035 | G11: 46037 | H11: 8000 | I11: 15 | J11: Montevideo, Salto | K11: Alquiler | M11: =+N11-H11 -> 229.55 | N11: =2200.7+2479.5+2745+804.35 -> 8229.55 | P11: =20+5 -> 25 | Q11: =+P11+O11 -> 25 | R11: =(N11/Q11) -> 329.182 | S11: =(('Costo por negocio'!$B$2-DATA!R11)*DATA!O11)+('Costo por negocio'!$C$2-DATA!R11)*DATA!P11 -> 1570.45 | T11: 46038 | U11: SI | V11: SI | W11: SI | Y11: BED 8545 | AA11: 94660 | AC11: 148 | AD11: 21718 | AE11: 46034.681 | AF11: 23015 | AG11: 46038.381 | AH11: =+AF11-AD11 -> 1297 | AI11: 3 | AJ11: =+AI11*5 -> 15 | AK11: =+Q11-AJ11 -> 10 | AM11: =+AH11/Q11 -> 51.88 | AN11: =+Q11/AI11 -> 8.3333333 | AQ11: =+N11/78.54 -> 104.78164 | AR11: =+AH11/11 -> 117.90909 | AS11: =+AR11-AQ11 -> 13.127451 | AT11: =+AH11/AQ11 -> 12.378123
A12: 11 | B12: Ignacio Ceroni | C12: 3007 | D12: 8 | E12: 01/01 al 14/01/2026 | F12: 46023 | G12: 46036 | J12: Montevideo | K12: Propio | M12: =+N12-H12 -> 3100 | N12: 3100 | O12: 16 | Q12: =+P12+O12 -> 16 | R12: =(N12/Q12) -> 193.75 | S12: =(('Costo por negocio'!$B$2-DATA!R12)*DATA!O12)+('Costo por negocio'!$C$2-DATA!R12)*DATA!P12 -> 1108 | T12: 46031 | U12: SI | V12: SI | W12: SI | Y12: SCG 4199 | AH12: =+AF12-AD12 -> 0 | AJ12: =+AI12*5 -> 0 | AK12: 0
A13: 12 | B13: Luis Amicone | C13: 3075 | D13: 8 | E13: 01/01 al 14/01/2026 | F13: 46023 | G13: 46036 | J13: Montevideo | K13: Propio | M13: =+N13-H13 -> 1500 | N13: 1500 | O13: 3 | Q13: =+P13+O13 -> 3 | R13: =(N13/Q13) -> 500 | S13: =(('Costo por negocio'!$B$2-DATA!R13)*DATA!O13)+('Costo por negocio'!$C$2-DATA!R13)*DATA!P13 -> -711 | T13: 46031 | U13: SI | V13: SI | W13: SI | Y13: SDD 5511 | AH13: =+AF13-AD13 -> 0 | AJ13: =+AI13*5 -> 0 | AK13: 0
A14: 13 | B14: Leonardo de Tomas | C14: 3076 | D14: 6 | E14: 01/01 al 12/01/2026 | F14: 46023 | G14: 46034 | J14: Montevideo, Colonia, Maldonado | K14: Propio | M14: =+N14-H14 -> 11729.1 | N14: =2831+2637.1+2900+3361 -> 11729.1 | P14: =18+12 -> 30 | Q14: =+P14+O14 -> 30 | R14: =(N14/Q14) -> 390.97 | S14: =(('Costo por negocio'!$B$2-DATA!R14)*DATA!O14)+('Costo por negocio'!$C$2-DATA!R14)*DATA!P14 -> 30.9 | T14: 46034 | U14: SI | V14: SI | W14: SI | Y14: SCN 5181 | AH14: =+AF14-AD14 -> 0 | AJ14: =+AI14*5 -> 0 | AK14: 0
A15: 14 | B15: Rolando Ball | C15: 1332 | D15: 8 | E15: 01/01 al 14/01/2026 | F15: 46023 | G15: 46036 | J15: Rocha | K15: Propio | M15: =+N15-H15 -> 7000 | N15: =1000+1800+2400+1800 -> 7000 | O15: 21 | P15: 4 | Q15: =+P15+O15 -> 25 | R15: =(N15/Q15) -> 280 | S15: =(('Costo por negocio'!$B$2-DATA!R15)*DATA!O15)+('Costo por negocio'!$C$2-DATA!R15)*DATA!P15 -> 91 | T15: 46037 | U15: SI | V15: SI | W15: SI | Y15: CBD 1303
A16: 15 | B16: Agustin Buñevaz | C16: 3152 | D16: 8 | E16: 01/01 al 14/01/2026 | F16: 46023 | G16: 46036 | J16: Montevideo, Canelones | K16: Propio | M16: =+N16-H16 -> 6312 | N16: =792+1056+1052+1052+2360 -> 6312 | O16: 23 | Q16: =+P16+O16 -> 23 | R16: =(N16/Q16) -> 274.43478 | S16: =(('Costo por negocio'!$B$2-DATA!R16)*DATA!O16)+('Costo por negocio'!$C$2-DATA!R16)*DATA!P16 -> -263 | T16: 46037 | U16: SI | V16: SI | W16: SI | Y16: ABK 2846
A17: 16 | B17: Lucia Santamaría | C17: 3065 | D17: 8 | E17: 01/01 al 14/01/2026 | F17: 46023 | G17: 46036 | J17: Maldonado | K17: Propio | M17: =+N17-H17 -> 6675.4 | N17: =2553+1322.4+2800 -> 6675.4 | O17: =20+6 -> 26 | Q17: =+P17+O17 -> 26 | R17: =(N17/Q17) -> 256.74615 | S17: =(('Costo por negocio'!$B$2-DATA!R17)*DATA!O17)+('Costo por negocio'!$C$2-DATA!R17)*DATA!P17 -> 162.6 | T17: 46037 | U17: SI | V17: SI | W17: SI | Y17: SBI 6680
A18: 17 | B18: Claudia Parrilla | C18: 2005 | D18: 3 | E18: 20/01 al 22/01/2026 | F18: 46042 | G18: 46044 | H18: =18*392 -> 7056 | I18: 15 | J18: Montevideo, Colonia | K18: Alquiler | M18: =+N18-H18 -> -4240 | N18: 2816 | O18: 4 | P18: 20 | Q18: =+P18+O18 -> 24 | R18: =(N18/Q18) -> 117.33333 | S18: =(('Costo por negocio'!$B$2-DATA!R18)*DATA!O18)+('Costo por negocio'!$C$2-DATA!R18)*DATA!P18 -> 6076 | T18: 46045 | U18: SI | V18: SI | W18: SI | Y18: BAA 7043 | AA18: 94705 | AC18: 111 | AD18: 80374 | AE18: 46042.375 | AF18: 80408 | AG18: 46045.388 | AH18: =+AF18-AD18 -> 34 | AI18: 3 | AJ18: =+AI18*5 -> 15 | AK18: =+Q18-AJ18 -> 9 | AM18: =+AH18/Q18 -> 1.4166667 | AN18: =+Q18/AI18 -> 8 | AQ18: =+N18/78.54 -> 35.854342 | AR18: =+AH18/11 -> 3.0909091 | AS18: =+AR18-AQ18 -> -32.763433 | AT18: =+AH18/AQ18 -> 0.94828125
A19: 18 | B19: Lucia Santamaría | C19: 3065 | D19: 12 | E19: 15/01 al 31/01/2026 | F19: 46037 | G19: 46053 | J19: Maldonado | K19: Propio | M19: =+N19-H19 -> 600.5 | N19: 600.5 | O19: 9 | Q19: =+P19+O19 -> 9 | R19: =(N19/Q19) -> 66.722222 | S19: =(('Costo por negocio'!$B$2-DATA!R19)*DATA!O19)+('Costo por negocio'!$C$2-DATA!R19)*DATA!P19 -> 1766.5 | T19: 46037 | U19: SI | V19: SI | W19: SI | Y19: SBI 6680 | AH19: =+AF19-AD19 -> 0 | AJ19: =+AI19*5 -> 0 | AK19: =+Q19-AJ19 -> 9
A20: 19 | B20: Claudia Parrilla | C20: 2005 | D20: 3 | E20: 27/01 al 29/01/2026 | F20: 46049 | G20: 46051 | H20: =18*263 -> 4734 | I20: 15 | J20: Montevideo | K20: Alquiler | M20: =+N20-H20 -> -1683.41 | N20: 3050.59 | O20: =20+6 -> 26 | Q20: =+P20+O20 -> 26 | R20: =(N20/Q20) -> 117.33038 | S20: =(('Costo por negocio'!$B$2-DATA!R20)*DATA!O20)+('Costo por negocio'!$C$2-DATA!R20)*DATA!P20 -> 3787.41 | T20: 46052 | U20: SI | V20: SI | W20: SI | Y20: BEB 4233 | AA20: 94749 | AC20: 111 | AD20: 109722 | AE20: 46049.375 | AF20: 110060 | AG20: 46052.375 | AH20: =+AF20-AD20 -> 338 | AI20: 3 | AJ20: =+AI20*5 -> 15 | AK20: =+Q20-AJ20 -> 11 | AM20: =+AH20/Q20 -> 13 | AN20: =+Q20/AI20 -> 8.6666667 | AQ20: =+N20/78.54 -> 38.841227 | AR20: =+AH20/11 -> 30.727273 | AS20: =+AR20-AQ20 -> -8.1139547 | AT20: =+AH20/AQ20 -> 8.7020937
A21: 20 | B21: Lorena Cabrera | C21: 1618 | D21: 3 | E21: 27/01 al 29/01/2026 | F21: 46049 | G21: 46051 | H21: 4500 | I21: 15 | J21: Canelones, Maldonado | K21: Alquiler | M21: =+N21-H21 -> 256.1 | N21: =2000+2000+756.1 -> 4756.1 | O21: 11 | Q21: =+P21+O21 -> 11 | R21: =(N21/Q21) -> 432.37273 | S21: =(('Costo por negocio'!$B$2-DATA!R21)*DATA!O21)+('Costo por negocio'!$C$2-DATA!R21)*DATA!P21 -> -1863.1 | T21: 46056 | U21: SI | V21: SI | W21: SI | Y21: BEB 8412 | AA21: 93095 | AC21: 111 | AD21: 107721 | AE21: 46048.708 | AF21: 108502 | AG21: 46052.375 | AH21: =+AF21-AD21 -> 781 | AI21: 3 | AJ21: =+AI21*5 -> 15 | AK21: =+Q21-AJ21 -> -4
A22: 21 | B22: Ignacio Ceroni | C22: 3007 | D22: 4 | E22: 19/01 al 22/01/2026 | F22: 46041 | G22: 46044 | I22: 20 | J22: Montevideo | K22: Alquiler | M22: =+N22-H22 -> 3300.6 | N22: 3300.6 | O22: =18+11 -> 29 | Q22: =+P22+O22 -> 29 | R22: =(N22/Q22) -> 113.81379 | S22: =(('Costo por negocio'!$B$2-DATA!R22)*DATA!O22)+('Costo por negocio'!$C$2-DATA!R22)*DATA!P22 -> 4326.4 | T22: 46045 | U22: SI | V22: SI | W22: SI | Y22: BED 6748 | AA22: 94703 | AC22: 146 | AD22: 97593 | AE22: 46041.393 | AF22: 98027 | AG22: 46045.381 | AH22: =+AF22-AD22 -> 434 | AI22: 4 | AJ22: =+AI22*5 -> 20 | AK22: =+Q22-AJ22 -> 9 | AM22: =+AH22/Q22 -> 14.965517 | AN22: =+Q22/AI22 -> 7.25 | AQ22: =+N22/78.54 -> 42.024446 | AR22: =+AH22/11 -> 39.454545 | AS22: =+AR22-AQ22 -> -2.5699007 | AT22: =+AH22/AQ22 -> 10.327322
A23: 22 | B23: Ignacio Ceroni | C23: 3007 | D23: 12 | E23: 15/01 al 31/01/2026 | F23: 46037 | G23: 46053 | J23: Montevideo | K23: Propio | M23: =+N23-H23 -> 4568.1 | N23: =1800+2768.1 -> 4568.1 | O23: 9 | P23: 6 | Q23: =+P23+O23 -> 15 | R23: =(N23/Q23) -> 304.54 | S23: =(('Costo por negocio'!$B$2-DATA!R23)*DATA!O23)+('Costo por negocio'!$C$2-DATA!R23)*DATA!P23 -> 150.9 | T23: 46045 | U23: SI | V23: SI | W23: SI | Y23: SCG 4199 | AH23: =+AF23-AD23 -> 0 | AJ23: =+AI23*5 -> 0 | AK23: =+Q23-AJ23 -> 15
A24: 23 | B24: Lorena Cabrera | C24: 1618 | D24: 3 | E24: 20/01 al 22/01/2026 | F24: 46042 | G24: 46044 | I24: 15 | J24: Canelones, Maldonado | K24: Alquiler | M24: =+N24-H24 -> 3125.4 | N24: =2770.9+354.5 -> 3125.4 | O24: 10 | Q24: =+P24+O24 -> 10 | R24: =(N24/Q24) -> 312.54 | S24: =(('Costo por negocio'!$B$2-DATA!R24)*DATA!O24)+('Costo por negocio'!$C$2-DATA!R24)*DATA!P24 -> -495.4 | T24: 46049 | U24: SI | V24: SI | W24: SI | Y24: AAL 4305 | AA24: 93069 | AC24: 110 | AD24: 106904 | AE24: 46042.375 | AF24: 107433 | AG24: 46045.375 | AH24: =+AF24-AD24 -> 529 | AI24: 2 | AJ24: =+AI24*5 -> 10 | AK24: =+Q24-AJ24 -> 0 | AM24: =+AH24/Q24 -> 52.9 | AN24: =+Q24/AI24 -> 5 | AQ24: =+N24/78.54 -> 39.793736 | AR24: =+AH24/11 -> 48.090909 | AS24: =+AR24-AQ24 -> 8.2971734 | AT24: =+AH24/AQ24 -> 13.29355
A25: 24 | B25: Agustin Buñevaz | C25: 3152 | D25: 2 | E25: 22/01 al 23/01/2026 | F25: 46044 | G25: 46045 | I25: 10 | J25: Montevideo, Canelones | K25: Alquiler | M25: =+N25-H25 -> 2630 | N25: 2630 | O25: 10 | Q25: =+P25+O25 -> 10 | R25: =(N25/Q25) -> 263 | S25: =(('Costo por negocio'!$B$2-DATA!R25)*DATA!O25)+('Costo por negocio'!$C$2-DATA!R25)*DATA!P25 -> 0 | T25: 46049 | U25: SI | V25: SI | W25: SI | Y25: AAL 4328 | AA25: 93071 | AC25: 74 | AD25: 66471 | AE25: 46043.749 | AF25: 66806 | AG25: 46045.744 | AH25: =+AF25-AD25 -> 335 | AI25: 2 | AJ25: =+AI25*5 -> 10 | AK25: =+Q25-AJ25 -> 0 | AM25: =+AH25/Q25 -> 33.5 | AN25: =+Q25/AI25 -> 5 | AQ25: =+N25/78.54 -> 33.486122 | AR25: =+AH25/11 -> 30.454545 | AS25: =+AR25-AQ25 -> -3.0315763 | AT25: =+AH25/AQ25 -> 10.004144
A26: 25 | B26: Ricardo Cardona | C26: 1512 | D26: 3 | E26: 03/02 al 05/02/2026 | F26: 46056 | G26: 46058 | H26: 7000 | I26: 15 | J26: Montevideo, Río Negro | K26: Alquiler | M26: =+N26-H26 -> -592.2 | N26: =2065+2410+1932.8 -> 6407.8 | P26: 7 | Q26: =+P26+O26 -> 7 | R26: =(N26/Q26) -> 915.4 | S26: =(('Costo por negocio'!$B$2-DATA!R26)*DATA!O26)+('Costo por negocio'!$C$2-DATA!R26)*DATA!P26 -> -3663.8 | T26: 46049 | U26: SI | V26: SI | W26: SI | Y26: BEC 5528 | AA26: 94791 | AC26: 111 | AD26: 83208 | AE26: 46055.667 | AF26: 84167 | AG26: 46059.388 | AH26: =+AF26-AD26 -> 959 | AI26: 3 | AJ26: =+AI26*5 -> 15 | AK26: =+Q26-AJ26 -> -8 | AM26: =+AH26/Q26 -> 137 | AN26: =+Q26/AI26 -> 2.3333333 | AQ26: =+N26/78.54 -> 81.586453 | AR26: =+AH26/11 -> 87.181818 | AS26: =+AR26-AQ26 -> 5.5953654 | AT26: =+AH26/AQ26 -> 11.754402
A27: 26 | B27: Lorena Cabrera | C27: 1618 | D27: 3 | E27: 03/02 al 05/02/2026 | F27: 46056 | G27: 46058 | H27: 4500 | I27: 15 | J27: Canelones, Maldonado | K27: Alquiler | M27: =+N27-H27 -> -283.7 | N27: =2654.1+1562.2 -> 4216.3 | O27: 8 | Q27: =+P27+O27 -> 8 | R27: =(N27/Q27) -> 527.0375 | S27: =(('Costo por negocio'!$B$2-DATA!R27)*DATA!O27)+('Costo por negocio'!$C$2-DATA!R27)*DATA!P27 -> -2112.3 | T27: 46063 | U27: SI | V27: SI | W27: SI | Y27: BEC 5947 | AA27: 93099 | AC27: 111 | AD27: 71872 | AE27: 46055.708 | AF27: 72794 | AG27: 46059.403 | AH27: =+AF27-AD27 -> 922 | AI27: 3 | AJ27: =+AI27*5 -> 15 | AK27: =+Q27-AJ27 -> -7 | AM27: =+AH27/Q27 -> 115.25 | AN27: =+Q27/AI27 -> 2.6666667 | AQ27: =+N27/78.54 -> 53.683473 | AR27: =+AH27/11 -> 83.818182 | AS27: =+AR27-AQ27 -> 30.134708 | AT27: =+AH27/AQ27 -> 17.174746
A28: 27 | B28: Luis Amicone | C28: 3075 | D28: 3 | E28: 03/02 al 05/02/2026 | F28: 46056 | G28: 46058 | H28: 8000 | I28: 15 | J28: Montevideo, Salto | K28: Alquiler | M28: =+N28-H28 -> 1794.5 | N28: =1550+3848.1+2896.4+1500 -> 9794.5 | P28: =20+2 -> 22 | Q28: =+P28+O28 -> 22 | R28: =(N28/Q28) -> 445.20455 | S28: =(('Costo por negocio'!$B$2-DATA!R28)*DATA!O28)+('Costo por negocio'!$C$2-DATA!R28)*DATA!P28 -> -1170.5 | T28: 46059 | U28: SI | V28: SI | W28: SI | Y28: BED 2527 | AA28: 94790 | AC28: 111 | AD28: 101160 | AE28: 46055.663 | AF28: 102532 | AG28: 46059.379 | AH28: =+AF28-AD28 -> 1372 | AI28: 3 | AJ28: =+AI28*5 -> 15 | AK28: =+Q28-AJ28 -> 7 | AM28: =+AH28/Q28 -> 62.363636 | AN28: =+Q28/AI28 -> 7.3333333 | AQ28: =+N28/78.54 -> 124.70716 | AR28: =+AH28/11 -> 124.72727 | AS28: =+AR28-AQ28 -> 0.020117138 | AT28: =+AH28/AQ28 -> 11.001774
A29: 28 | B29: Natalia Greco | C29: 3154 | D29: 3 | E29: 03/02 al 05/02/2026 | F29: 46056 | G29: 46058 | H29: 5000 | I29: 15 | J29: Montevideo, San José | K29: Alquiler | M29: =+N29-H29 -> -1149 | N29: =1550+2301 -> 3851 | O29: =9+6 -> 15 | P29: 1 | Q29: =+P29+O29 -> 16 | R29: =(N29/Q29) -> 240.6875 | S29: =(('Costo por negocio'!$B$2-DATA!R29)*DATA!O29)+('Costo por negocio'!$C$2-DATA!R29)*DATA!P29 -> 486 | T29: 46059 | U29: SI | V29: SI | W29: SI | Y29: BED 7113 | AA29: 94781 | AC29: 111 | AD29: 108264 | AE29: 46055.708 | AF29: 108840 | AG29: 46058.673 | AH29: =+AF29-AD29 -> 576 | AI29: 3 | AJ29: =+AI29*5 -> 15 | AK29: =+Q29-AJ29 -> 1 | AM29: =+AH29/Q29 -> 36 | AN29: =+Q29/AI29 -> 5.3333333 | AQ29: =+N29/78.54 -> 49.03234 | AR29: =+AH29/11 -> 52.363636 | AS29: =+AR29-AQ29 -> 3.3312962 | AT29: =+AH29/AQ29 -> 11.747349
A30: 29 | B30: Luis Amicone | C30: 3075 | D30: 12 | E30: 15/01 al 31/01/2026 | F30: 46037 | G30: 46053 | J30: Montevideo | K30: Propio | M30: =+N30-H30 -> 7500 | N30: =2000+1000+2000+2000+500 -> 7500 | O30: =16+11 -> 27 | Q30: =+P30+O30 -> 27 | R30: =(N30/Q30) -> 277.77778 | S30: =(('Costo por negocio'!$B$2-DATA!R30)*DATA!O30)+('Costo por negocio'!$C$2-DATA!R30)*DATA!P30 -> -399 | T30: 46052 | U30: SI | V30: SI | W30: SI | Y30: SDA 5511
A31: 30 | B31: Rolando Ball | C31: 1332 | D31: 12 | E31: 15/01 al 31/01/2026 | F31: 46037 | G31: 46053 | J31: Rocha | K31: Propio | M31: =+N31-H31 -> 6300 | N31: =2000+2300+2000 -> 6300 | O31: =16+2 -> 18 | P31: 4 | Q31: =+P31+O31 -> 22 | R31: =(N31/Q31) -> 286.36364 | S31: =(('Costo por negocio'!$B$2-DATA!R31)*DATA!O31)+('Costo por negocio'!$C$2-DATA!R31)*DATA!P31 -> 2 | T31: 46056 | U31: SI | V31: SI | W31: SI | Y31: CBD 1303
A32: 31 | B32: Agustin Buñevaz | C32: 3152 | D32: 12 | E32: 15/01 al 31/01/2026 | F32: 46037 | G32: 46053 | J32: Montevideo, Canelones | K32: Propio | M32: =+N32-H32 -> 6312 | N32: =1052+1315+789+466+789+1052+849 -> 6312 | O32: =20+4 -> 24 | Q32: =+P32+O32 -> 24 | R32: =(N32/Q32) -> 263 | S32: =(('Costo por negocio'!$B$2-DATA!R32)*DATA!O32)+('Costo por negocio'!$C$2-DATA!R32)*DATA!P32 -> 0 | T32: 46056 | U32: SI | V32: SI | W32: SI | Y32: SBK 2846
A33: 32 | B33: Sylvia Antunez | C33: 3064 | D33: 12 | E33: 15/01 al 31/01/2026 | F33: 46037 | G33: 46053 | J33: Montevideo, Canelones | K33: Propio | M33: =+N33-H33 -> 2114 | N33: 2114 | O33: =11+5+6+1 -> 23 | Q33: =+P33+O33 -> 23 | R33: =(N33/Q33) -> 91.913043 | S33: =(('Costo por negocio'!$B$2-DATA!R33)*DATA!O33)+('Costo por negocio'!$C$2-DATA!R33)*DATA!P33 -> 3935 | T33: 46056 | U33: SI | V33: SI | W33: SI | Y33: SDD 4937
A34: 33 | B34: Fernando López | C34: 3117 | D34: 12 | E34: 15/01 al 31/01/2026 | F34: 46037 | G34: 46053 | J34: Montevideo | K34: Propio | M34: =+N34-H34 -> 5500.6 | N34: =3000+2500.6 -> 5500.6 | O34: =11+10 -> 21 | Q34: =+P34+O34 -> 21 | R34: =(N34/Q34) -> 261.93333 | S34: =(('Costo por negocio'!$B$2-DATA!R34)*DATA!O34)+('Costo por negocio'!$C$2-DATA!R34)*DATA!P34 -> 22.4 | T34: 46056 | U34: SI | V34: SI | W34: SI | Y34: SCL 8868
A35: 34 | B35: Claudia Parrilla | C35: 2005 | D35: 3 | E35: 10/02 al 12/02/2026 | F35: 46063 | G35: 46065 | H35: =30*392 -> 11760 | I35: 15 | J35: Montevideo, Artigas | K35: Alquiler | M35: =+N35-H35 -> -4188.2 | N35: =2527+2349.5+1428.6+1266.7 -> 7571.8 | P35: =20+2 -> 22 | Q35: =+P35+O35 -> 22 | R35: =(N35/Q35) -> 344.17273 | S35: =(('Costo por negocio'!$B$2-DATA!R35)*DATA!O35)+('Costo por negocio'!$C$2-DATA!R35)*DATA!P35 -> 1052.2 | T35: 46066 | U35: SI | V35: SI | W35: SI | Y35: BEB 9257 | AA35: 95450 | AC35: 111 | AD35: 81267 | AE35: 46062.708 | AF35: 82641 | AG35: 46066.388 | AH35: =+AF35-AD35 -> 1374 | AI35: 3 | AJ35: =+AI35*5 -> 15 | AK35: =+Q35-AJ35 -> 7 | AM35: =+AH35/Q35 -> 62.454545 | AN35: =+Q35/AI35 -> 7.3333333 | AQ35: =+N35/78.54 -> 96.406926 | AR35: =+AH35/11 -> 124.90909 | AS35: =+AR35-AQ35 -> 28.502165 | AT35: =+AH35/AQ35 -> 14.252088
A36: 35 | B36: Ricardo Cardona | C36: 1512 | D36: 3 | E36: 10/02 al 12/02/2026 | F36: 46063 | G36: 46065 | H36: 6000 | I36: 15 | J36: Montevideo, Flores, Durazno | K36: Alquiler | M36: =+N36-H36 -> -1479.8 | N36: =2200+1820.2+500 -> 4520.2 | P36: 10 | Q36: =+P36+O36 -> 10 | R36: =(N36/Q36) -> 452.02 | S36: =(('Costo por negocio'!$B$2-DATA!R36)*DATA!O36)+('Costo por negocio'!$C$2-DATA!R36)*DATA!P36 -> -600.2 | T36: 46066 | U36: SI | V36: SI | W36: SI | Y36: BEC 5478 | AA36: 95446 | AC36: 111 | AD36: 78049 | AE36: 46062.66 | AF36: 78681 | AG36: 46066.378 | AH36: =+AF36-AD36 -> 632 | AI36: 3 | AJ36: =+AI36*5 -> 15 | AK36: =+Q36-AJ36 -> -5 | AM36: =+AH36/Q36 -> 63.2 | AN36: =+Q36/AI36 -> 3.3333333 | AQ36: =+N36/78.54 -> 57.552839 | AR36: =+AH36/11 -> 57.454545 | AS36: =+AR36-AQ36 -> -0.098293863 | AT36: =+AH36/AQ36 -> 10.981213
A37: 36 | B37: Fernando López | C37: 3117 | D37: 3 | E37: 10/02 al 12/02/2026 | F37: 46063 | G37: 46065 | H37: 3000 | I37: 15 | J37: Montevideo | K37: Alquiler | M37: =+N37-H37 -> 571.2 | N37: =2200.5+1370.7 -> 3571.2 | O37: 6 | P37: 11 | Q37: =+P37+O37 -> 17 | R37: =(N37/Q37) -> 210.07059 | S37: =(('Costo por negocio'!$B$2-DATA!R37)*DATA!O37)+('Costo por negocio'!$C$2-DATA!R37)*DATA!P37 -> 2318.8 | T37: 46066 | U37: SI | V37: SI | W37: SI | Y37: BEC 2029 | AA37: 95447 | AC37: 111 | AD37: 131518 | AE37: 46062.708 | AF37: 132048 | AG37: 46066.382 | AH37: =+AF37-AD37 -> 530 | AI37: 3 | AJ37: =+AI37*5 -> 15 | AK37: =+Q37-AJ37 -> 2 | AM37: =+AH37/Q37 -> 31.176471 | AN37: =+Q37/AI37 -> 5.6666667 | AQ37: =+N37/78.54 -> 45.469824 | AR37: =+AH37/11 -> 48.181818 | AS37: =+AR37-AQ37 -> 2.7119939 | AT37: =+AH37/AQ37 -> 11.656082
A38: 37 | B38: Ignacio Ceroni | C38: 3007 | D38: 4 | E38: 09/02 al 12/02/2026 | F38: 46062 | G38: 46065 | H38: 3000 | I38: 20 | J38: Montevideo | K38: Alquiler | M38: =+N38-H38 -> 467.1 | N38: =3066.5+400.6 -> 3467.1 | O38: =20+10 -> 30 | Q38: =+P38+O38 -> 30 | R38: =(N38/Q38) -> 115.57 | S38: =(('Costo por negocio'!$B$2-DATA!R38)*DATA!O38)+('Costo por negocio'!$C$2-DATA!R38)*DATA!P38 -> 4422.9 | T38: 46066 | U38: SI | V38: SI | W38: SI | Y38: BEC 5634 | AA38: 95449 | AC38: 148 | AD38: 82664 | AE38: 46062.375 | AF38: 83123 | AG38: 46066.385 | AH38: =+AF38-AD38 -> 459 | AI38: 4 | AJ38: =+AI38*5 -> 20 | AK38: =+Q38-AJ38 -> 10 | AM38: =+AH38/Q38 -> 15.3 | AN38: =+Q38/AI38 -> 7.5 | AQ38: =+N38/78.54 -> 44.144385 | AR38: =+AH38/11 -> 41.727273 | AS38: =+AR38-AQ38 -> -2.4171123 | AT38: =+AH38/AQ38 -> 10.397698
A39: 38 | B39: Luis Amicone | C39: 3075 | D39: 3 | E39: 10/02 al 12/02/2026 | F39: 46063 | G39: 46065 | H39: 8000 | I39: 15 | J39: Montevideo, Tacuarembo | K39: Alquiler | M39: =+N39-H39 -> -780.6 | N39: =2901+2800.4+1518 -> 7219.4 | P39: =20+1 -> 21 | Q39: =+P39+O39 -> 21 | R39: =(N39/Q39) -> 343.78095 | S39: =(('Costo por negocio'!$B$2-DATA!R39)*DATA!O39)+('Costo por negocio'!$C$2-DATA!R39)*DATA!P39 -> 1012.6 | T39: 46066 | U39: SI | V39: SI | W39: SI | Y39: BED 2529 | AA39: 95435 / NC 13549 | AC39: =111-37 -> 74 | AD39: 79309 | AE39: 46062.667 | AF39: 80279 | AG39: 46065.382 | AH39: =+AF39-AD39 -> 970 | AI39: 2 | AJ39: =+AI39*5 -> 10 | AK39: =+Q39-AJ39 -> 11 | AM39: =+AH39/Q39 -> 46.190476 | AN39: =+Q39/AI39 -> 10.5 | AQ39: =+N39/78.54 -> 91.920041 | AR39: =+AH39/11 -> 88.181818 | AS39: =+AR39-AQ39 -> -3.7382226 | AT39: =+AH39/AQ39 -> 10.55265
A40: 39 | B40: Lorena Cabrera | C40: 1618 | D40: 3 | E40: 10/02 al 12/02/2026 | F40: 46063 | G40: 46065 | H40: 4500 | I40: 15 | J40: Canelones, Maldonado, Lavalleja | K40: Alquiler | M40: =+N40-H40 -> 1000.8 | N40: =2500.3+3000.5 -> 5500.8 | O40: 9 | P40: 3 | Q40: =+P40+O40 -> 12 | R40: =(N40/Q40) -> 458.4 | S40: =(('Costo por negocio'!$B$2-DATA!R40)*DATA!O40)+('Costo por negocio'!$C$2-DATA!R40)*DATA!P40 -> -1957.8 | T40: 46073 | U40: SI | V40: SI | W40: SI | Y40: BEB 9280 | AA40: 93119 | AC40: 111 | AD40: 99981 | AE40: 46062.708 | AF40: 101018 | AG40: 46066.403 | AH40: =+AF40-AD40 -> 1037 | AI40: 3 | AJ40: =+AI40*5 -> 15 | AK40: =+Q40-AJ40 -> -3 | AM40: =+AH40/Q40 -> 86.416667 | AN40: =+Q40/AI40 -> 4 | AQ40: =+N40/78.54 -> 70.038197 | AR40: =+AH40/11 -> 94.272727 | AS40: =+AR40-AQ40 -> 24.23453 | AT40: =+AH40/AQ40 -> 14.806206
A41: 40 | B41: Fernando López | C41: 3117 | D41: 8 | E41: 01/02 al 11/02/2026 | F41: 46054 | G41: 46064 | H41: 2500 | I41: =+H41/263 -> 9.5057034 | J41: Montevideo | K41: Propio | M41: =+N41-H41 -> 0 | N41: 2500 | O41: 9 | Q41: =+P41+O41 -> 9 | R41: =(N41/Q41) -> 277.77778 | S41: =(('Costo por negocio'!$B$2-DATA!R41)*DATA!O41)+('Costo por negocio'!$C$2-DATA!R41)*DATA!P41 -> -133 | T41: 46064 | U41: SI | V41: SI | W41: SI | Y41: SCL 8868
A42: 41 | B42: Agustin Buñevaz | C42: 3152 | D42: 8 | E42: 01/02 al 11/02/2026 | F42: 46054 | G42: 46064 | J42: Montevideo, Canelones | K42: Propio | M42: =+N42-H42 -> 3409 | N42: =1052+1052+522+783 -> 3409 | O42: 13 | Q42: =+P42+O42 -> 13 | R42: =(N42/Q42) -> 262.23077 | S42: =(('Costo por negocio'!$B$2-DATA!R42)*DATA!O42)+('Costo por negocio'!$C$2-DATA!R42)*DATA!P42 -> 10 | T42: 46063 | U42: SI | V42: SI | W42: SI | Y42: ABK 2846
A43: 42 | B43: Sylvia Antunez | C43: 3064 | D43: 3 | E43: 03/02 al 05/02/2026 | F43: 46056 | G43: 46058 | J43: Montevideo | K43: Propio | M43: =+N43-H43 -> 2500 | N43: 2500 | O43: 11 | Q43: =+P43+O43 -> 11 | R43: =(N43/Q43) -> 227.27273 | S43: =(('Costo por negocio'!$B$2-DATA!R43)*DATA!O43)+('Costo por negocio'!$C$2-DATA!R43)*DATA!P43 -> 393 | T43: 46063 | U43: SI | V43: SI | W43: SI | Y43: BAB 1469 | AA43: 94785 | AC43: 111 | AD43: 107476 | AE43: 46055.729 | AF43: 107689 | AG43: 46058.722 | AH43: =+AF43-AD43 -> 213 | AI43: 3 | AJ43: =+AI43*5 -> 15 | AK43: =+Q43-AJ43 -> -4 | AM43: =+AH43/Q43 -> 19.363636 | AN43: =+Q43/AI43 -> 3.6666667 | AQ43: =+N43/78.54 -> 31.830914 | AR43: =+AH43/11 -> 19.363636 | AS43: =+AR43-AQ43 -> -12.467278 | AT43: =+AH43/AQ43 -> 6.691608
A44: 43 | B44: Rolando Ball | C44: 1332 | D44: 8 | E44: 01/02 al 11/02/2026 | F44: 46054 | G44: 46064 | J44: Rocha | K44: Propio | M44: =+N44-H44 -> 4500 | N44: =1800+900+1800 -> 4500 | O44: 10 | P44: 5 | Q44: =+P44+O44 -> 15 | R44: =(N44/Q44) -> 300 | S44: =(('Costo por negocio'!$B$2-DATA!R44)*DATA!O44)+('Costo por negocio'!$C$2-DATA!R44)*DATA!P44 -> 90 | T44: 46065 | U44: SI | V44: SI | W44: SI | Y44: CBD 1303
A45: 44 | B45: Lucia Santamaría | C45: 3065 | D45: 8 | E45: 01/02 al 11/02/2026 | F45: 46054 | G45: 46064 | J45: Maldonado | K45: Propio | M45: =+N45-H45 -> 5251 | N45: =2800+2451 -> 5251 | O45: =20+4 -> 24 | Q45: =+P45+O45 -> 24 | R45: =(N45/Q45) -> 218.79167 | S45: =(('Costo por negocio'!$B$2-DATA!R45)*DATA!O45)+('Costo por negocio'!$C$2-DATA!R45)*DATA!P45 -> 1061 | T45: 46065 | U45: SI | V45: SI | W45: SI | Y45: SBI 6680
A46: 45 | B46: Claudia Parrilla | C46: 2005 | D46: 2 | E46: 19/02 al 20/02/2026 | F46: 46072 | G46: 46073 | H46: =12*263 -> 3156 | I46: 15 | J46: Montevideo | K46: Alquiler | M46: =+N46-H46 -> -809.4 | N46: 2346.6 | O46: 16 | Q46: =+P46+O46 -> 16 | R46: =(N46/Q46) -> 146.6625 | S46: =(('Costo por negocio'!$B$2-DATA!R46)*DATA!O46)+('Costo por negocio'!$C$2-DATA!R46)*DATA!P46 -> 1861.4 | T46: 46073 | U46: SI | V46: SI | W46: SI | Y46: BEB 4233 | AA46: 95479 | AC46: 74 | AD46: 111906 | AE46: 46071.396 | AF46: 112489 | AG46: 46073.382 | AH46: =+AF46-AD46 -> 583 | AI46: 2 | AJ46: =+AI46*5 -> 10 | AK46: =+Q46-AJ46 -> 6 | AM46: =+AH46/Q46 -> 36.4375 | AN46: =+Q46/AI46 -> 8 | AQ46: =+N46/78.54 -> 29.877769 | AR46: =+AH46/11 -> 53 | AS46: =+AR46-AQ46 -> 23.122231 | AT46: =+AH46/AQ46 -> 19.512836
A47: 46 | B47: Fernando López | C47: 3117 | D47: 10 | E47: 12/02 al 28/02/2026 | F47: 46065 | G47: 46081 | H47: 5000 | I47: =+H47/263 -> 19.011407 | J47: Montevideo | K47: Propio | M47: =+N47-H47 -> -2000 | N47: 3000 | O47: =10+9 -> 19 | Q47: =+P47+O47 -> 19 | R47: =(N47/Q47) -> 157.89474 | S47: =(('Costo por negocio'!$B$2-DATA!R47)*DATA!O47)+('Costo por negocio'!$C$2-DATA!R47)*DATA!P47 -> 1997 | T47: 46083 | U47: SI | V47: SI | W47: SI | Y47: SCL 8868 | Z47: 46084
A48: 47 | B48: Claudia Parrilla | C48: 2005 | D48: 3 | E48: 24/02 al 26/02/2026 | F48: 46077 | G48: 46079 | H48: =12*263 -> 3156 | I48: 15 | J48: Montevideo | K48: Alquiler | M48: =+N48-H48 -> 970.9 | N48: =376.9+3750 -> 4126.9 | O48: =20+2 -> 22 | Q48: =+P48+O48 -> 22 | R48: =(N48/Q48) -> 187.58636 | S48: =(('Costo por negocio'!$B$2-DATA!R48)*DATA!O48)+('Costo por negocio'!$C$2-DATA!R48)*DATA!P48 -> 1659.1 | T48: 46080 | U48: SI | V48: SI | W48: SI | Y48: BED 6748 | AA48: 95563 | AC48: 111 | AD48: 102684 | AE48: 46077.375 | AF48: 103344 | AG48: 46080.392 | AH48: =+AF48-AD48 -> 660 | AI48: 3 | AJ48: =+AI48*5 -> 15 | AK48: =+Q48-AJ48 -> 7 | AM48: =+AH48/Q48 -> 30 | AN48: =+Q48/AI48 -> 7.3333333 | AQ48: =+N48/78.54 -> 52.5452 | AR48: =+AH48/11 -> 60 | AS48: =+AR48-AQ48 -> 7.4548001 | AT48: =+AH48/AQ48 -> 12.560615
A49: 48 | B49: Ignacio Ceroni | C49: 3007 | D49: 4 | E49: 23/02 al 26/02/2026 | F49: 46076 | G49: 46079 | H49: 6000 | I49: 20 | J49: Montevideo, Paysandú | K49: Alquiler | M49: =+N49-H49 -> 1668 | N49: =2980+2900+1788 -> 7668 | O49: =7+5 -> 12 | P49: =13+13 -> 26 | Q49: =+P49+O49 -> 38 | R49: =(N49/Q49) -> 201.78947 | S49: =(('Costo por negocio'!$B$2-DATA!R49)*DATA!O49)+('Costo por negocio'!$C$2-DATA!R49)*DATA!P49 -> 5680 | T49: 46073 | U49: SI | V49: SI | W49: SI | Y49: BEB 9057 | AA49: 95531 | AC49: 148 | AD49: 84444 | AE49: 46076.396 | AF49: 85823 | AG49: 46080.4 | AH49: =+AF49-AD49 -> 1379 | AI49: 4 | AJ49: =+AI49*5 -> 20 | AK49: =+Q49-AJ49 -> 18 | AM49: =+AH49/Q49 -> 36.289474 | AN49: =+Q49/AI49 -> 9.5 | AQ49: =+N49/78.54 -> 97.63178 | AR49: =+AH49/11 -> 125.36364 | AS49: =+AR49-AQ49 -> 27.731856 | AT49: =+AH49/AQ49 -> 14.124499
A50: 49 | B50: Ricardo Cardona | C50: 1512 | D50: 3 | E50: 24/02 al 26/02/2026 | F50: 46077 | G50: 46079 | H50: 7000 | I50: 15 | J50: Montevideo, Paysandú | K50: Alquiler | M50: =+N50-H50 -> 845.4 | N50: =2300+2107+2043.2+1395.2 -> 7845.4 | P50: 10 | Q50: =+P50+O50 -> 10 | R50: =(N50/Q50) -> 784.54 | S50: =(('Costo por negocio'!$B$2-DATA!R50)*DATA!O50)+('Costo por negocio'!$C$2-DATA!R50)*DATA!P50 -> -3925.4 | T50: 46073 | U50: SI | V50: SI | W50: SI | Y50: BED 8126 | AA50: 95525 | AC50: 111 | AD50: 121844 | AE50: 46076.708 | AF50: 123017 | AG50: 46080.382 | AH50: =+AF50-AD50 -> 1173 | AI50: 3 | AJ50: =+AI50*5 -> 15 | AK50: =+Q50-AJ50 -> -5 | AM50: =+AH50/Q50 -> 117.3 | AN50: =+Q50/AI50 -> 3.3333333 | AQ50: =+N50/78.54 -> 99.890502 | AR50: =+AH50/11 -> 106.63636 | AS50: =+AR50-AQ50 -> 6.745862 | AT50: =+AH50/AQ50 -> 11.742858
A51: 50 | B51: Luis Amicone | C51: 3075 | D51: 3 | E51: 24/02 al 26/02/2026 | F51: 46077 | G51: 46079 | H51: 7000 | I51: 15 | J51: Montevideo, Soriano | K51: Alquiler | M51: =+N51-H51 -> -1329.7 | N51: =1950+1172.3+2342+206 -> 5670.3 | P51: 20 | Q51: =+P51+O51 -> 20 | R51: =(N51/Q51) -> 283.515 | S51: =(('Costo por negocio'!$B$2-DATA!R51)*DATA!O51)+('Costo por negocio'!$C$2-DATA!R51)*DATA!P51 -> 2169.7 | T51: 46073 | U51: SI | V51: SI | W51: SI | Y51: BEC 5477 | AA51: 95519 | AC51: 74 | AD51: 83063 | AE51: 46076.667 | AF51: 84037 | AG51: 46079.389 | AH51: =+AF51-AD51 -> 974 | AI51: 2 | AJ51: =+AI51*5 -> 10 | AK51: =+Q51-AJ51 -> 10 | AM51: =+AH51/Q51 -> 48.7 | AN51: =+Q51/AI51 -> 10 | AQ51: =+N51/78.54 -> 72.196333 | AR51: =+AH51/11 -> 88.545455 | AS51: =+AR51-AQ51 -> 16.349121 | AT51: =+AH51/AQ51 -> 13.49099
A52: 51 | B52: Fernando López | C52: 3117 | D52: 3 | E52: 24/02 al 26/02/2026 | F52: 46077 | G52: 46079 | H52: 4000 | I52: 15 | J52: Montevideo | K52: Alquiler | T52: 46073 | U52: SI | V52: SI | W52: SI | X52: Para descontar
A53: 52 | B53: Ignacio Ceroni | C53: 3007 | D53: 3 | E53: 18/02 al 20/02/2026 | F53: 46071 | G53: 46073 | I53: 15 | J53: Montevideo | K53: Alquiler | M53: =+N53-H53 -> 2780 | N53: 2780 | O53: 20 | Q53: =+P53+O53 -> 20 | R53: =(N53/Q53) -> 139 | S53: =(('Costo por negocio'!$B$2-DATA!R53)*DATA!O53)+('Costo por negocio'!$C$2-DATA!R53)*DATA!P53 -> 2480 | T53: 46073 | U53: SI | V53: SI | W53: SI | Y53: BED 6748 | AA53: 95491 | AC53: 111 | AD53: 101712 | AE53: 46071.375 | AF53: 102075 | AG53: 46073.719 | AH53: =+AF53-AD53 -> 363 | AI53: 3 | AJ53: =+AI53*5 -> 15 | AK53: =+Q53-AJ53 -> 5 | AM53: =+AH53/Q53 -> 18.15 | AN53: =+Q53/AI53 -> 6.6666667 | AQ53: =+N53/78.54 -> 35.395977 | AR53: =+AH53/11 -> 33 | AS53: =+AR53-AQ53 -> -2.3959766 | AT53: =+AH53/AQ53 -> 10.255403
A54: 53 | B54: Natalia Greco | C54: 3154 | D54: 2 | E54: 18/02 al 19/02/2026 | F54: 46071 | G54: 46072 | I54: 15 | J54: Montevideo, Colonia | K54: Alquiler | M54: =+N54-H54 -> 3050.1 | N54: 3050.1 | O54: 7 | P54: 7 | Q54: =+P54+O54 -> 14 | R54: =(N54/Q54) -> 217.86429 | S54: =(('Costo por negocio'!$B$2-DATA!R54)*DATA!O54)+('Costo por negocio'!$C$2-DATA!R54)*DATA!P54 -> 1534.9 | T54: 46073 | U54: SI | V54: SI | W54: SI | Y54: BAB 1469 | AA54: 95478 | AC54: 74 | AD54: 110468 | AE54: 46071.375 | AF54: 110598 | AG54: 46073.378 | AH54: =+AF54-AD54 -> 130 | AI54: 3 | AJ54: =+AI54*5 -> 15 | AK54: =+Q54-AJ54 -> -1 | AM54: =+AH54/Q54 -> 9.2857143 | AN54: =+Q54/AI54 -> 4.6666667 | AQ54: =+N54/78.54 -> 38.834989 | AR54: =+AH54/11 -> 11.818182 | AS54: =+AR54-AQ54 -> -27.016807 | AT54: =+AH54/AQ54 -> 3.3474968
A55: 54 | B55: Lorena Cabrera | C55: 1618 | D55: 3 | E55: 24/02 al 26/02/2026 | F55: 46077 | G55: 46079 | H55: 4500 | I55: 15 | J55: Canelones, Maldonado | K55: Alquiler | M55: =+N55-H55 -> -49.8 | N55: =1000+3450.2 -> 4450.2 | P55: 7 | Q55: =+P55+O55 -> 7 | R55: =(N55/Q55) -> 635.74286 | S55: =(('Costo por negocio'!$B$2-DATA!R55)*DATA!O55)+('Costo por negocio'!$C$2-DATA!R55)*DATA!P55 -> -1706.2 | T55: 46083 | U55: SI | V55: SI | W55: SI | Y55: BED 2527 | Z55: 46084 | AA55: 93150 | AC55: 111 | AD55: 104115 | AE55: 46076.733 | AF55: 104875 | AG55: 46080.375 | AH55: =+AF55-AD55 -> 760 | AI55: 3 | AJ55: =+AI55*5 -> 15 | AK55: =+Q55-AJ55 -> -8 | AM55: =+AH55/Q55 -> 108.57143 | AN55: =+Q55/AI55 -> 2.3333333 | AQ55: =+N55/78.54 -> 56.661574 | AR55: =+AH55/11 -> 69.090909 | AS55: =+AR55-AQ55 -> 12.429335 | AT55: =+AH55/AQ55 -> 13.41297
A56: 55 | B56: Claudia Parrilla | C56: 2005 | D56: 3 | E56: 03/03 al 05/03/2026 | F56: 46084 | G56: 46086 | H56: =18*263 -> 4734 | I56: 15 | J56: Montevideo | K56: Alquiler | M56: =+N56-H56 -> -1702.37 | N56: =2781+250.63 -> 3031.63 | O56: 27 | Q56: =+P56+O56 -> 27 | R56: =(N56/Q56) -> 112.28259 | S56: =(('Costo por negocio'!$B$3-DATA!R56)*DATA!O56)+('Costo por negocio'!$C$3-DATA!R56)*DATA!P56 -> 3988.37 | T56: 46087 | U56: SI | V56: SI | W56: SI | Y56: BEC 5947 | Z56: 46087 | AA56: 95594 | AC56: 111 | AD56: 74661 | AE56: 46084.389 | AF56: 75074 | AG56: 46087.396 | AH56: =+AF56-AD56 -> 413 | AI56: 3 | AJ56: =+AI56*5 -> 15 | AK56: =+Q56-AJ56 -> 12 | AM56: =+AH56/Q56 -> 15.296296 | AN56: =+Q56/AI56 -> 9 | AQ56: =+N56/78.54 -> 38.599822 | AR56: =+AH56/11 -> 37.545455 | AS56: =+AR56-AQ56 -> -1.0543672 | AT56: =+AH56/AQ56 -> 10.699531
A57: 56 | B57: Ricardo Cardona | C57: 1512 | D57: 3 | E57: 03/03 al 05/03/2026 | F57: 46084 | G57: 46086 | H57: 6000 | I57: 15 | J57: Montevideo, Río Negro, Flores, Durazno | K57: Alquiler | M57: =+N57-H57 -> -99.5 | N57: =2200+1750+1950.5 -> 5900.5 | P57: 11 | Q57: =+P57+O57 -> 11 | R57: =(N57/Q57) -> 536.40909 | S57: =(('Costo por negocio'!$B$3-DATA!R57)*DATA!O57)+('Costo por negocio'!$C$3-DATA!R57)*DATA!P57 -> -1643.5 | T57: 46087 | U57: SI | V57: SI | W57: SI | Y57: BEC 5195 | Z57: 46087 | AA57: 95592 | AC57: 111 | AD57: 68679 | AE57: 46083.688 | AF57: 69586 | AG57: 46087.389 | AH57: =+AF57-AD57 -> 907 | AI57: 3 | AJ57: =+AI57*5 -> 15 | AK57: =+Q57-AJ57 -> -4 | AM57: =+AH57/Q57 -> 82.454545 | AN57: =+Q57/AI57 -> 3.6666667 | AQ57: =+N57/78.54 -> 75.127324 | AR57: =+AH57/11 -> 82.454545 | AS57: =+AR57-AQ57 -> 7.3272218 | AT57: =+AH57/AQ57 -> 12.072838
A58: 57 | B58: Ignacio Ceroni | C58: 3007 | D58: 4 | E58: 02/03 al 05/03/2026 | F58: 46083 | G58: 46086 | H58: 5000 | I58: 20 | J58: Montevideo, Durazno | K58: Alquiler | M58: =+N58-H58 -> 369.3 | N58: =2530+2839.3 -> 5369.3 | O58: =6+11 -> 17 | P58: 14 | Q58: =+P58+O58 -> 31 | R58: =(N58/Q58) -> 173.20323 | S58: =(('Costo por negocio'!$B$3-DATA!R58)*DATA!O58)+('Costo por negocio'!$C$3-DATA!R58)*DATA!P58 -> 4468.7 | T58: 46087 | U58: SI | V58: SI | W58: SI | Y58: BEE 1555 | Z58: 46087 | AA58: 95593 | AC58: 148 | AD58: 7321 | AE58: 46083.375 | AF58: 8276 | AG58: 46087.392 | AH58: =+AF58-AD58 -> 955 | AI58: 3 | AJ58: =+AI58*5 -> 15 | AK58: =+Q58-AJ58 -> 16 | AM58: =+AH58/Q58 -> 30.806452 | AN58: =+Q58/AI58 -> 10.333333 | AQ58: =+N58/78.54 -> 68.363891 | AR58: =+AH58/11 -> 86.818182 | AS58: =+AR58-AQ58 -> 18.454291 | AT58: =+AH58/AQ58 -> 13.969363
A59: 58 | B59: Luis Amicone | C59: 3075 | D59: 3 | E59: 03/03 al 05/03/2026 | F59: 46084 | G59: 46086 | H59: 8000 | I59: 15 | J59: Montevideo, Soriano, Colonia | K59: Alquiler | M59: =+N59-H59 -> -3570.2 | N59: =2400+2029.8 -> 4429.8 | P59: 20 | Q59: =+P59+O59 -> 20 | R59: =(N59/Q59) -> 221.49 | S59: =(('Costo por negocio'!$B$3-DATA!R59)*DATA!O59)+('Costo por negocio'!$C$3-DATA!R59)*DATA!P59 -> 3310.2 | T59: 46087 | U59: SI | V59: SI | W59: SI | Y59: LAL 7289 | Z59: 46087 | AA59: 95584 | AC59: 74 | AD59: 122452 | AE59: 46083.708 | AF59: 123186 | AG59: 46086.385 | AH59: =+AF59-AD59 -> 734 | AI59: 2 | AJ59: =+AI59*5 -> 10 | AK59: =+Q59-AJ59 -> 10 | AM59: =+AH59/Q59 -> 36.7 | AN59: =+Q59/AI59 -> 10 | AQ59: =+N59/78.54 -> 56.401833 | AR59: =+AH59/11 -> 66.727273 | AS59: =+AR59-AQ59 -> 10.325439 | AT59: =+AH59/AQ59 -> 13.013761
A60: 59 | B60: Lorena Cabrera | C60: 1618 | D60: 3 | E60: 03/03 al 05/03/2026 | F60: 46084 | G60: 46086 | H60: 4500 | I60: 15 | J60: Canelones, Maldonado | K60: Alquiler | M60: =+N60-H60 -> 24.6 | N60: =1024.6+3500 -> 4524.6 | O60: 11 | Q60: =+P60+O60 -> 11 | R60: =(N60/Q60) -> 411.32727 | S60: =(('Costo por negocio'!$B$3-DATA!R60)*DATA!O60)+('Costo por negocio'!$C$3-DATA!R60)*DATA!P60 -> -1664.6 | T60: 46093 | U60: SI | V60: SI | W60: SI | Y60: BEB 8417 | Z60: 46094 | AA60: 93163 | AC60: 111 | AD60: 78212 | AE60: 46083.708 | AF60: 79101 | AG60: 46087.708 | AH60: =+AF60-AD60 -> 889 | AI60: 3 | AJ60: =+AI60*5 -> 15 | AK60: =+Q60-AJ60 -> -4 | AM60: =+AH60/Q60 -> 80.818182 | AN60: =+Q60/AI60 -> 3.6666667 | AQ60: =+N60/78.54 -> 57.608862 | AR60: =+AH60/11 -> 80.818182 | AS60: =+AR60-AQ60 -> 23.20932 | AT60: =+AH60/AQ60 -> 15.431654
A61: 60 | B61: Agustin Buñevaz | C61: 3152 | D61: 2 | E61: 25/02 al 26/02/2026 | F61: 46078 | G61: 46079 | I61: 10 | J61: Montevideo, Canelones | K61: Alquiler | M61: =+N61-H61 -> 1578 | N61: 1578 | O61: 6 | Q61: =+P61+O61 -> 6 | R61: =(N61/Q61) -> 263 | S61: =(('Costo por negocio'!$B$2-DATA!R61)*DATA!O61)+('Costo por negocio'!$C$2-DATA!R61)*DATA!P61 -> 0 | T61: 46083 | U61: SI | V61: SI | W61: SI | Y61: BEC 2019 | AA61: 87972 | AC61: 83 | AD61: 86505 | AE61: 46077.774 | AF61: 86931 | AG61: 46078.744 | AH61: =+AF61-AD61 -> 426 | AI61: 2 | AJ61: =+AI61*5 -> 10 | AK61: =+Q61-AJ61 -> -4 | AM61: =+AH61/Q61 -> 71 | AN61: =+Q61/AI61 -> 3 | AQ61: =+N61/78.54 -> 20.091673 | AR61: =+AH61/11 -> 38.727273 | AS61: =+AR61-AQ61 -> 18.6356 | AT61: =+AH61/AQ61 -> 21.202814
A62: 61 | B62: Luis Amicone | C62: 3075 | D62: 10 | E62: 12/02 al 28/02/2026 | F62: 46065 | G62: 46081 | J62: Montevideo | K62: Propio | M62: =+N62-H62 -> 3000 | N62: =2000+1000 -> 3000 | O62: =11+2 -> 13 | Q62: =+P62+O62 -> 13 | R62: =(N62/Q62) -> 230.76923 | S62: =(('Costo por negocio'!$B$2-DATA!R62)*DATA!O62)+('Costo por negocio'!$C$2-DATA!R62)*DATA!P62 -> 419 | T62: 46083 | U62: SI | V62: SI | W62: SI | Y62: SDA 5511 | Z62: 46084
A63: 62 | B63: Agustin Buñevaz | C63: 3152 | D63: 10 | E63: 12/02 al 28/02/2026 | F63: 46065 | G63: 46081 | J63: Montevideo, Canelones | K63: Propio | M63: =+N63-H63 -> 2883 | N63: =1052+779+1052 -> 2883 | O63: 11 | Q63: =+P63+O63 -> 11 | R63: =(N63/Q63) -> 262.09091 | S63: =(('Costo por negocio'!$B$2-DATA!R63)*DATA!O63)+('Costo por negocio'!$C$2-DATA!R63)*DATA!P63 -> 10 | T63: 46083 | U63: SI | V63: SI | W63: SI | Y63: ABK 2846 | Z63: 46084
A64: 63 | B64: Lucia Santamaría | C64: 3065 | D64: 10 | E64: 12/02 al 28/02/2026 | F64: 46065 | G64: 46081 | J64: Montevideo | K64: Propio | M64: =+N64-H64 -> 6244 | N64: =2613.6+2630+1000.4 -> 6244 | O64: =20+20+3 -> 43 | Q64: =+P64+O64 -> 43 | R64: =(N64/Q64) -> 145.2093 | S64: =(('Costo por negocio'!$B$2-DATA!R64)*DATA!O64)+('Costo por negocio'!$C$2-DATA!R64)*DATA!P64 -> 5065 | T64: 46083 | U64: SI | V64: SI | W64: SI | Y64: SBI 6680 | Z64: 46084
A65: 64 | B65: Rolando Ball | C65: 1332 | D65: 10 | E65: 12/02 al 28/02/2026 | F65: 46065 | G65: 46081 | J65: Rocha | K65: Propio | M65: =+N65-H65 -> 3750 | N65: =1900+1850 -> 3750 | O65: 4 | P65: 7 | Q65: =+P65+O65 -> 11 | R65: =(N65/Q65) -> 340.90909 | S65: =(('Costo por negocio'!$B$2-DATA!R65)*DATA!O65)+('Costo por negocio'!$C$2-DATA!R65)*DATA!P65 -> 46 | T65: 46083 | U65: SI | V65: SI | W65: SI | Y65: CBD 1303 | Z65: 46084
A66: 65 | B66: Claudia Parrilla | C66: 2005 | D66: 3 | E66: 10/03 al 12/03/2026 | F66: 46091 | G66: 46093 | H66: =20*260 -> 5200 | I66: 15 | J66: Montevideo | K66: Alquiler | M66: =+N66-H66 -> -1312.4 | N66: =2286.2+1601.4 -> 3887.6 | O66: =20+5 -> 25 | Q66: =+P66+O66 -> 25 | R66: =(N66/Q66) -> 155.504 | S66: =(('Costo por negocio'!$B$3-DATA!R66)*DATA!O66)+('Costo por negocio'!$C$3-DATA!R66)*DATA!P66 -> 2612.4 | T66: 46098 | U66: SI | V66: SI | W66: SI | Y66: BED 1333 | Z66: 46098 | AA66: 96642 | AC66: 111 | AD66: 40038 | AE66: 46090.729 | AF66: 40728 | AG66: 46094.382 | AH66: =+AF66-AD66 -> 690 | AI66: 3 | AJ66: =+AI66*5 -> 15 | AK66: =+Q66-AJ66 -> 10 | AM66: =+AH66/Q66 -> 27.6 | AN66: =+Q66/AI66 -> 8.3333333 | AQ66: =+N66/78.54 -> 49.498345 | AR66: =+AH66/11 -> 62.727273 | AS66: =+AR66-AQ66 -> 13.228928 | AT66: =+AH66/AQ66 -> 13.93986
A67: 66 | B67: Ricardo Cardona | C67: 1512 | D67: 3 | E67: 10/03 al 12/03/2026 | F67: 46091 | G67: 46093 | H67: 4500 | I67: 15 | J67: Montevideo, Flores | K67: Alquiler | M67: =+N67-H67 -> -699.5 | N67: =1700.4+2100.1 -> 3800.5 | P67: 9 | Q67: =+P67+O67 -> 9 | R67: =(N67/Q67) -> 422.27778 | S67: =(('Costo por negocio'!$B$3-DATA!R67)*DATA!O67)+('Costo por negocio'!$C$3-DATA!R67)*DATA!P67 -> -317.5 | T67: 46093 | U67: SI | V67: SI | W67: SI | Y67: BEC 5473 | Z67: 46094 | AA67: 96640 | AC67: 111 | AD67: 88518 | AE67: 46090.708 | AF67: 89125 | AG67: 46094.381 | AH67: =+AF67-AD67 -> 607 | AI67: 3 | AJ67: =+AI67*5 -> 15 | AK67: =+Q67-AJ67 -> -6 | AM67: =+AH67/Q67 -> 67.444444 | AN67: =+Q67/AI67 -> 3 | AQ67: =+N67/78.54 -> 48.389356 | AR67: =+AH67/11 -> 55.181818 | AS67: =+AR67-AQ67 -> 6.7924624 | AT67: =+AH67/AQ67 -> 12.544081
A68: 67 | B68: Natalia Greco | C68: 3154 | D68: 3 | E68: 10/03 al 12/03/2026 | F68: 46091 | G68: 46093 | H68: 5000 | I68: 15 | J68: Montevideo | K68: Alquiler | M68: =+N68-H68 -> -2479 | N68: 2521 | O68: =7+6 -> 13 | Q68: =+P68+O68 -> 13 | R68: =(N68/Q68) -> 193.92308 | S68: =(('Costo por negocio'!$B$3-DATA!R68)*DATA!O68)+('Costo por negocio'!$C$3-DATA!R68)*DATA!P68 -> 859 | T68: 46093 | U68: SI | V68: SI | W68: SI | Y68: BAB 3608 | Z68: 46094 | AA68: 96641 | AC68: 111 | AD68: 73410 | AE68: 46091.438 | AF68: 74034 | AG68: 46094.378 | AH68: =+AF68-AD68 -> 624 | AI68: 3 | AJ68: =+AI68*5 -> 15 | AK68: =+Q68-AJ68 -> -2 | AM68: =+AH68/Q68 -> 48 | AN68: =+Q68/AI68 -> 4.3333333 | AQ68: =+N68/78.54 -> 32.098294 | AR68: =+AH68/11 -> 56.727273 | AS68: =+AR68-AQ68 -> 24.628979 | AT68: =+AH68/AQ68 -> 19.440286
A69: 68 | B69: Luis Amicone | C69: 3075 | D69: 3 | E69: 10/03 al 12/03/2026 | F69: 46091 | G69: 46093 | H69: 8000 | I69: 15 | J69: Montevideo, Soriano | K69: Alquiler | M69: =+N69-H69 -> -3228.9 | N69: =2671+2100.1 -> 4771.1 | P69: =20+2 -> 22 | Q69: =+P69+O69 -> 22 | R69: =(N69/Q69) -> 216.86818 | S69: =(('Costo por negocio'!$B$3-DATA!R69)*DATA!O69)+('Costo por negocio'!$C$3-DATA!R69)*DATA!P69 -> 3742.9 | T69: 46093 | U69: SI | V69: SI | W69: SI | Y69: BEC 5530 | Z69: 46094 | AA69: 96631 | AC69: 111 | AD69: 91037 | AE69: 46090.667 | AF69: 91822 | AG69: 46093.375 | AH69: =+AF69-AD69 -> 785 | AI69: 2 | AJ69: =+AI69*5 -> 10 | AK69: =+Q69-AJ69 -> 12 | AM69: =+AH69/Q69 -> 35.681818 | AN69: =+Q69/AI69 -> 11 | AQ69: =+N69/78.54 -> 60.74739 | AR69: =+AH69/11 -> 71.363636 | AS69: =+AR69-AQ69 -> 10.616246 | AT69: =+AH69/AQ69 -> 12.922366
A70: 69 | B70: Lorena Cabrera | C70: 1618 | D70: 3 | E70: 10/03 al 12/03/2026 | F70: 46091 | G70: 46093 | H70: 4500 | I70: 15 | J70: Canelones, Lavalleja | K70: Alquiler | M70: =+N70-H70 -> -1149.2 | N70: =1960+1390.8 -> 3350.8 | O70: 8 | Q70: =+P70+O70 -> 8 | R70: =(N70/Q70) -> 418.85 | S70: =(('Costo por negocio'!$B$3-DATA!R70)*DATA!O70)+('Costo por negocio'!$C$3-DATA!R70)*DATA!P70 -> -1270.8 | T70: 46101 | U70: SI | V70: SI | W70: SI | Y70: BEC 5787 | Z70: 46101 | AA70: 93180 | AC70: 111 | AD70: 58655 | AE70: 46090.708 | AF70: 59463 | AG70: 46094.375 | AH70: =+AF70-AD70 -> 808 | AI70: 2 | AJ70: =+AI70*5 -> 10 | AK70: =+Q70-AJ70 -> -2 | AM70: =+AH70/Q70 -> 101 | AN70: =+Q70/AI70 -> 4 | AQ70: =+N70/78.54 -> 42.663611 | AR70: =+AH70/11 -> 73.454545 | AS70: =+AR70-AQ70 -> 30.790935 | AT70: =+AH70/AQ70 -> 18.938856
A71: 70 | B71: Ignacio Ceroni | C71: 3007 | D71: 4 | E71: 09/03 al 12/03/2026 | F71: 46090 | G71: 46093 | H71: 3000 | I71: 20 | J71: Montevideo | K71: Alquiler | M71: =+N71-H71 -> 1160.55 | N71: =2800+1360.55 -> 4160.55 | O71: =7+12 -> 19 | P71: =13+2 -> 15 | Q71: =+P71+O71 -> 34 | R71: =(N71/Q71) -> 122.36912 | S71: =(('Costo por negocio'!$B$3-DATA!R71)*DATA!O71)+('Costo por negocio'!$C$3-DATA!R71)*DATA!P71 -> 6584.45 | T71: 46094 | U71: SI | V71: SI | W71: SI | Y71: BEC 5531 | Z71: 46094 | AA71: 96644 | AC71: 148 | AD71: 71550 | AE71: 46090.375 | AF71: 72231 | AG71: 46094.397 | AH71: =+AF71-AD71 -> 681 | AI71: 4 | AJ71: =+AI71*5 -> 20 | AK71: =+Q71-AJ71 -> 14 | AM71: =+AH71/Q71 -> 20.029412 | AN71: =+Q71/AI71 -> 8.5 | AQ71: =+N71/78.54 -> 52.973644 | AR71: =+AH71/11 -> 61.909091 | AS71: =+AR71-AQ71 -> 8.9354469 | AT71: =+AH71/AQ71 -> 12.855449
A72: 71 | B72: Gabriela Falero | C72: 2030 | D72: 3 | E72: 03/03 al 05/03/2026 | F72: 46084 | G72: 46086 | I72: 15 | J72: Montevideo, Rivera | K72: Alquiler | M72: =+N72-H72 -> 9944.9 | N72: =3000.6+3844+3100.3 -> 9944.9 | P72: =20+18 -> 38 | Q72: =+P72+O72 -> 38 | R72: =(N72/Q72) -> 261.70789 | S72: =(('Costo por negocio'!$B$3-DATA!R72)*DATA!O72)+('Costo por negocio'!$C$3-DATA!R72)*DATA!P72 -> 4761.1 | T72: 46087 | U72: SI | V72: SI | W72: SI | Y72: BEB 4216 | Z72: 46087 | AA72: 95595 | AC72: 111 | AD72: 88875 | AE72: 46083.688 | AF72: 90127 | AG72: 46087.396 | AH72: =+AF72-AD72 -> 1252 | AI72: 3 | AJ72: =+AI72*5 -> 15 | AK72: =+Q72-AJ72 -> 23 | AM72: =+AH72/Q72 -> 32.947368 | AN72: =+Q72/AI72 -> 12.666667 | AQ72: =+N72/78.54 -> 126.6221 | AR72: =+AH72/11 -> 113.81818 | AS72: =+AR72-AQ72 -> -12.803922 | AT72: =+AH72/AQ72 -> 9.8876892 | AU72: Fernando Lopez | AV72: Natalia Greco | AY72: 1
A73: 72 | B73: Lucia Santamaría | C73: 3065 | D73: 8 | E73: 01/03 al 11/03/2026 | F73: 46082 | G73: 46092 | J73: Montevideo | K73: Propio | M73: =+N73-H73 -> 4637.1 | N73: =2650.1+1987 -> 4637.1 | O73: =19+5 -> 24 | Q73: =+P73+O73 -> 24 | R73: =(N73/Q73) -> 193.2125 | S73: =(('Costo por negocio'!$B$3-DATA!R73)*DATA!O73)+('Costo por negocio'!$C$3-DATA!R73)*DATA!P73 -> 1602.9 | T73: 46093 | U73: SI | V73: SI | W73: SI | Y73: SBI 6680 | Z73: 46094
A74: 73 | B74: Sylvia Antunez | C74: 3064 | D74: 3 | E74: 03/02 al 05/02/2026 | F74: 46056 | G74: 46058 | J74: Montevideo, Canelones | K74: Propio | M74: =+N74-H74 -> 2340 | N74: 2340 | O74: =9+3 -> 12 | Q74: =+P74+O74 -> 12 | R74: =(N74/Q74) -> 195 | S74: =(('Costo por negocio'!$B$3-DATA!R74)*DATA!O74)+('Costo por negocio'!$C$3-DATA!R74)*DATA!P74 -> 780 | T74: 46093 | U74: SI | V74: SI | W74: SI | Y74: SDD 4937 | Z74: 46094
A75: 74 | B75: Sylvia Antunez | C75: 3064 | D75: 3 | E75: 03/02 al 05/02/2026 | F75: 46056 | G75: 46058 | I75: 15 | J75: Montevideo, Canelones | K75: Alquiler | M75: =+N75-H75 -> 750 | N75: 750 | O75: 9 | Q75: =+P75+O75 -> 9 | R75: =(N75/Q75) -> 83.333333 | S75: =(('Costo por negocio'!$B$3-DATA!R75)*DATA!O75)+('Costo por negocio'!$C$3-DATA!R75)*DATA!P75 -> 1590 | T75: 46093 | U75: SI | V75: SI | W75: SI | Y75: BED 8551 | Z75: 46094 | AA75: 96630 | AC75: 74 | AD75: 15590 | AE75: 46091.389 | AF75: 15763 | AG75: 46092.747 | AH75: =+AF75-AD75 -> 173 | AI75: 2 | AJ75: =+AI75*5 -> 10 | AK75: =+Q75-AJ75 -> -1 | AM75: =+AH75/Q75 -> 19.222222 | AN75: =+Q75/AI75 -> 4.5 | AQ75: =+N75/78.54 -> 9.5492743 | AR75: =+AH75/11 -> 15.727273 | AS75: =+AR75-AQ75 -> 6.1779985 | AT75: =+AH75/AQ75 -> 18.11656
A76: 75 | B76: Agustin Buñevaz | C76: 3152 | D76: 8 | E76: 01/03 al 11/03/2026 | F76: 46082 | G76: 46092 | J76: Montevideo, Canelones | K76: Propio | M76: =+N76-H76 -> 7799.04 | N76: =2050+1300.04+1859+789+1031+770 -> 7799.04 | O76: =20+10 -> 30 | Q76: =+P76+O76 -> 30 | R76: =(N76/Q76) -> 259.968 | S76: =(('Costo por negocio'!$B$3-DATA!R76)*DATA!O76)+('Costo por negocio'!$C$3-DATA!R76)*DATA!P76 -> 0.96 | T76: 46093 | U76: SI | V76: SI | W76: SI | Y76: ABK 2846 | Z76: 46094
A77: 76 | B77: Claudia Parrilla | C77: 2005 | D77: 3 | E77: 17/03 al 19/03/2026 | F77: 46098 | G77: 46100 | H77: =20*260 -> 5200 | I77: 15 | J77: Montevideo, San José | K77: Alquiler | M77: =+N77-H77 -> -2315.8 | N77: 2884.2 | O77: =19+2 -> 21 | Q77: =+P77+O77 -> 21 | R77: =(N77/Q77) -> 137.34286 | S77: =(('Costo por negocio'!$B$3-DATA!R77)*DATA!O77)+('Costo por negocio'!$C$3-DATA!R77)*DATA!P77 -> 2575.8 | T77: 46105 | U77: SI | V77: SI | W77: SI | Y77: BAB 1952 | Z77: 46105 | AA77: 96699 | AC77: 111 | AD77: 113081 | AE77: 46097.708 | AF77: 113512 | AG77: 46101.38 | AH77: =+AF77-AD77 -> 431 | AI77: 3 | AJ77: =+AI77*5 -> 15 | AK77: =+Q77-AJ77 -> 6 | AM77: =+AH77/Q77 -> 20.52381 | AN77: =+Q77/AI77 -> 7 | AQ77: =+N77/78.54 -> 36.722689 | AR77: =+AH77/11 -> 39.181818 | AS77: =+AR77-AQ77 -> 2.4591291 | AT77: =+AH77/AQ77 -> 11.736613
A78: 77 | B78: Ricardo Cardona | C78: 1512 | D78: 3 | E78: 17/03 al 19/03/2026 | F78: 46098 | G78: 46100 | H78: 6500 | I78: 15 | J78: Montevideo, Canelones | K78: Alquiler | X78: Para descontar salio con Falero
A79: 78 | B79: Fernando López | C79: 3117 | D79: 3 | E79: 17/03 al 19/03/2026 | F79: 46098 | G79: 46100 | H79: 5000 | I79: 15 | J79: Montevideo, Colonia | K79: Alquiler | M79: =+N79-H79 -> -2811.2 | N79: 2188.8 | O79: =11+11 -> 22 | Q79: =+P79+O79 -> 22 | R79: =(N79/Q79) -> 99.490909 | S79: =(('Costo por negocio'!$B$3-DATA!R79)*DATA!O79)+('Costo por negocio'!$C$3-DATA!R79)*DATA!P79 -> 3531.2 | T79: 46101 | U79: SI | V79: SI | W79: SI | Y79: BED 2527 | Z79: 46101 | AA79: 96697 | AC79: 111 | AD79: 106418 | AE79: 46098.438 | AF79: 106694 | AG79: 46101.378 | AH79: =+AF79-AD79 -> 276 | AI79: 3 | AJ79: =+AI79*5 -> 15 | AK79: =+Q79-AJ79 -> 7 | AM79: =+AH79/Q79 -> 12.545455 | AN79: =+Q79/AI79 -> 7.3333333 | AQ79: =+N79/78.54 -> 27.868602 | AR79: =+AH79/11 -> 25.090909 | AS79: =+AR79-AQ79 -> -2.7776929 | AT79: =+AH79/AQ79 -> 9.9036184
A80: 79 | B80: Ignacio Ceroni | C80: 3007 | D80: 4 | E80: 16/03 al 19/03/2026 | F80: 46097 | G80: 46100 | H80: 6000 | I80: 20 | J80: Montevideo, Cerro Largo | K80: Alquiler | M80: =+N80-H80 -> 1798.8 | N80: =2601.6+2302+2895.2 -> 7798.8 | O80: =8+6 -> 14 | P80: =12+14 -> 26 | Q80: =+P80+O80 -> 40 | R80: =(N80/Q80) -> 194.97 | S80: =(('Costo por negocio'!$B$3-DATA!R80)*DATA!O80)+('Costo por negocio'!$C$3-DATA!R80)*DATA!P80 -> 5903.2 | T80: 46101 | U80: SI | V80: SI | W80: SI | Y80: BEC 5947 | Z80: 46101 | AA80: 96703 | AC80: 148 | AD80: 76119 | AE80: 46097.375 | AF80: 77500 | AG80: 46101.412 | AH80: =+AF80-AD80 -> 1381 | AI80: 4 | AJ80: =+AI80*5 -> 20 | AK80: =+Q80-AJ80 -> 20 | AM80: =+AH80/Q80 -> 34.525 | AN80: =+Q80/AI80 -> 10 | AQ80: =+N80/78.54 -> 99.297173 | AR80: =+AH80/11 -> 125.54545 | AS80: =+AR80-AQ80 -> 26.248281 | AT80: =+AH80/AQ80 -> 13.907747
A81: 80 | B81: Lucia Santamaría | C81: 3065 | D81: 14 | E81: 12/03 al 31/03/2026 | F81: 46093 | G81: 46112 | H81: 8000 | I81: 31 | J81: Montevideo | K81: Propio | X81: Para descontar tuvo un accidente y esta usando auto alquiler.
A82: 81 | B82: Claudia Parrilla | C82: 2005 | D82: 3 | E82: 24/03 al 26/03/2026 | F82: 46105 | G82: 46107 | H82: =20*260 -> 5200 | I82: 15 | J82: Montevideo, San José | K82: Alquiler | M82: =+N82-H82 -> -1440.29 | N82: =3659+100.71 -> 3759.71 | O82: 17 | Q82: =+P82+O82 -> 17 | R82: =(N82/Q82) -> 221.15941 | S82: =(('Costo por negocio'!$B$3-DATA!R82)*DATA!O82)+('Costo por negocio'!$C$3-DATA!R82)*DATA!P82 -> 660.29 | T82: 46112 | U82: SI | V82: SI | W82: SI | Y82: BEB 8417 | Z82: 46112 | AA82: 96756 | AC82: 111 | AD82: 81181 | AE82: 46104.688 | AF82: 81858 | AG82: 46108.375 | AH82: =+AF82-AD82 -> 677 | AI82: 3 | AJ82: =+AI82*5 -> 15 | AK82: =+Q82-AJ82 -> 2 | AM82: =+AH82/Q82 -> 39.823529 | AN82: =+Q82/AI82 -> 5.6666667 | AQ82: =+N82/78.54 -> 47.870003 | AR82: =+AH82/11 -> 61.545455 | AS82: =+AR82-AQ82 -> 13.675452 | AT82: =+AH82/AQ82 -> 14.142468
A83: 82 | B83: Ricardo Cardona | C83: 1512 | D83: 3 | E83: 24/03 al 26/03/2026 | F83: 46105 | G83: 46107 | H83: 4000 | I83: 15 | J83: Montevideo | K83: Alquiler | M83: =+N83-H83 -> -2699.9 | N83: 1300.1 | O83: 6 | Q83: =+P83+O83 -> 6 | R83: =(N83/Q83) -> 216.68333 | S83: =(('Costo por negocio'!$B$3-DATA!R83)*DATA!O83)+('Costo por negocio'!$C$3-DATA!R83)*DATA!P83 -> 259.9 | T83: 46108 | U83: SI | V83: SI | W83: SI | Y83: BEC 5485 | Z83: 46108 | AA83: 96758 | AC83: 111 | AD83: 53704 | AE83: 46104.688 | AF83: 53866 | AG83: 46108.381 | AH83: =+AF83-AD83 -> 162 | AI83: 3 | AJ83: =+AI83*5 -> 15 | AK83: =+Q83-AJ83 -> -9 | AM83: =+AH83/Q83 -> 27 | AN83: =+Q83/AI83 -> 2 | AQ83: =+N83/78.54 -> 16.553349 | AR83: =+AH83/11 -> 14.727273 | AS83: =+AR83-AQ83 -> -1.8260759 | AT83: =+AH83/AQ83 -> 9.7865395
A84: 83 | B84: Lorena Cabrera | C84: 1618 | D84: 3 | E84: 24/03 al 26/03/2026 | F84: 46105 | G84: 46107 | H84: 4500 | I84: 15 | J84: Canelones | K84: Alquiler | M84: =+N84-H84 -> -826.5 | N84: =2176.5+1497 -> 3673.5 | O84: 10 | Q84: =+P84+O84 -> 10 | R84: =(N84/Q84) -> 367.35 | S84: =(('Costo por negocio'!$B$3-DATA!R84)*DATA!O84)+('Costo por negocio'!$C$3-DATA!R84)*DATA!P84 -> -1073.5 | T84: 46112 | U84: SI | V84: SI | W84: SI | Y84: BED 3013 | Z84: 46112 | AA84: 95008 | AC84: 111 | AD84: 127400 | AE84: 46104.708 | AF84: 128235 | AG84: 46108.375 | AH84: =+AF84-AD84 -> 835 | AI84: 3 | AJ84: =+AI84*5 -> 15 | AK84: =+Q84-AJ84 -> -5 | AM84: =+AH84/Q84 -> 83.5 | AN84: =+Q84/AI84 -> 3.3333333 | AQ84: =+N84/78.54 -> 46.772345 | AR84: =+AH84/11 -> 75.909091 | AS84: =+AR84-AQ84 -> 29.136746 | AT84: =+AH84/AQ84 -> 17.85243
A85: 84 | B85: Luis Amicone | C85: 3075 | D85: 3 | E85: 24/03 al 26/03/2026 | F85: 46105 | G85: 46107 | H85: 8000 | I85: 15 | J85: Montevideo, Salto | K85: Alquiler | M85: =+N85-H85 -> -100 | N85: =1053.5+2600.1+2246.4+1500+500 -> 7900 | P85: =20+6 -> 26 | Q85: =+P85+O85 -> 26 | R85: =(N85/Q85) -> 303.84615 | S85: =(('Costo por negocio'!$B$3-DATA!R85)*DATA!O85)+('Costo por negocio'!$C$3-DATA!R85)*DATA!P85 -> 2162 | T85: 46108 | U85: SI | V85: SI | W85: SI | Y85: BEC 5530 | Z85: 46108 | AA85: 96760 | AC85: 111 | AD85: 93373 | AE85: 46104.708 | AF85: 94693 | AG85: 46108.384 | AH85: =+AF85-AD85 -> 1320 | AI85: 3 | AJ85: =+AI85*5 -> 15 | AK85: =+Q85-AJ85 -> 11 | AM85: =+AH85/Q85 -> 50.769231 | AN85: =+Q85/AI85 -> 8.6666667 | AQ85: =+N85/78.54 -> 100.58569 | AR85: =+AH85/11 -> 120 | AS85: =+AR85-AQ85 -> 19.414311 | AT85: =+AH85/AQ85 -> 13.123139
A86: 85 | B86: Ignacio Ceroni | C86: 3007 | D86: 4 | E86: 23/03 al 26/03/2026 | F86: 46104 | G86: 46107 | H86: 3000 | I86: 20 | J86: Montevideo | K86: Alquiler | M86: =+N86-H86 -> 320.86 | N86: =2920.7+400.16 -> 3320.86 | O86: =20+13 -> 33 | Q86: =+P86+O86 -> 33 | R86: =(N86/Q86) -> 100.63212 | S86: =(('Costo por negocio'!$B$3-DATA!R86)*DATA!O86)+('Costo por negocio'!$C$3-DATA!R86)*DATA!P86 -> 5259.14 | T86: 46108 | U86: SI | V86: SI | W86: SI | Y86: BEC 5477 | Z86: 46108 | AA86: 96761 | AC86: 148 | AD86: 85980 | AE86: 46104.444 | AF86: 86654 | AG86: 46108.396 | AH86: =+AF86-AD86 -> 674 | AI86: 4 | AJ86: =+AI86*5 -> 20 | AK86: =+Q86-AJ86 -> 13 | AM86: =+AH86/Q86 -> 20.424242 | AN86: =+Q86/AI86 -> 8.25 | AQ86: =+N86/78.54 -> 42.282404 | AR86: =+AH86/11 -> 61.272727 | AS86: =+AR86-AQ86 -> 18.990323 | AT86: =+AH86/AQ86 -> 15.940437
A87: 86 | B87: Agustin Buñevaz | C87: 3152 | D87: 2 | E87: 18/03 al 19/03/2026 | F87: 46099 | G87: 46100 | I87: 10 | J87: Canelones, Lavalleja | K87: Alquiler | M87: =+N87-H87 -> 2201 | N87: 2201 | O87: 4 | P87: 3 | Q87: =+P87+O87 -> 7 | R87: =(N87/Q87) -> 314.42857 | S87: =(('Costo por negocio'!$B$3-DATA!R87)*DATA!O87)+('Costo por negocio'!$C$3-DATA!R87)*DATA!P87 -> 0 | T87: 46101 | U87: SI | V87: SI | W87: SI | Y87: BED 7113 | Z87: 46101 | AD87: 112853 | AE87: 46098.708 | AF87: 113282 | AG87: 46100.75 | AH87: =+AF87-AD87 -> 429 | AI87: 2 | AJ87: =+AI87*5 -> 10 | AK87: =+Q87-AJ87 -> -3 | AM87: =+AH87/Q87 -> 61.285714 | AN87: =+Q87/AI87 -> 3.5 | AQ87: =+N87/78.54 -> 28.023937 | AR87: =+AH87/11 -> 39 | AS87: =+AR87-AQ87 -> 10.976063 | AT87: =+AH87/AQ87 -> 15.308342
A88: 87 | B88: Luis Amicone | C88: 3075 | D88: 2 | E88: 17/03 al 18/03/2026 | F88: 46098 | G88: 46099 | I88: 15 | J88: Montevideo, Treinta y Tres | K88: Alquiler | M88: =+N88-H88 -> 5572.1 | N88: =2620.1+2952 -> 5572.1 | P88: =20+6 -> 26 | Q88: =+P88+O88 -> 26 | R88: =(N88/Q88) -> 214.31154 | S88: =(('Costo por negocio'!$B$3-DATA!R88)*DATA!O88)+('Costo por negocio'!$C$3-DATA!R88)*DATA!P88 -> 4489.9 | T88: 46101 | U88: SI | V88: SI | W88: SI | Y88: BED 9321 | Z88: 46101 | AA88: 96681 | AC88: 74 | AD88: 114913 | AE88: 46097.688 | AF88: 115766 | AG88: 46100.379 | AH88: =+AF88-AD88 -> 853 | AI88: 2 | AJ88: =+AI88*5 -> 10 | AK88: =+Q88-AJ88 -> 16 | AM88: =+AH88/Q88 -> 32.807692 | AN88: =+Q88/AI88 -> 13 | AQ88: =+N88/78.54 -> 70.946015 | AR88: =+AH88/11 -> 77.545455 | AS88: =+AR88-AQ88 -> 6.5994398 | AT88: =+AH88/AQ88 -> 12.023226
A89: 88 | B89: Gabriela Falero | C89: 2030 | D89: 3 | E89: 17/03 al 19/03/2026 | F89: 46098 | G89: 46100 | I89: 15 | J89: Montevideo, Maldonado, Canelones | K89: Alquiler | M89: =+N89-H89 -> 6340.3 | N89: =2139.2+2250.4+1950.7 -> 6340.3 | O89: 5 | P89: 11 | Q89: =+P89+O89 -> 16 | R89: =(N89/Q89) -> 396.26875 | S89: =(('Costo por negocio'!$B$3-DATA!R89)*DATA!O89)+('Costo por negocio'!$C$3-DATA!R89)*DATA!P89 -> -783.3 | T89: 46101 | U89: SI | V89: SI | W89: SI | Y89: BEB 9280 | Z89: 46101 | AA89: 96700 | AC89: 111 | AD89: 104261 | AE89: 46097.667 | AF89: 105154 | AG89: 46101.382 | AH89: =+AF89-AD89 -> 893 | AI89: 3 | AJ89: =+AI89*5 -> 15 | AK89: =+Q89-AJ89 -> 1 | AM89: =+AH89/Q89 -> 55.8125 | AN89: =+Q89/AI89 -> 5.3333333 | AQ89: =+N89/78.54 -> 80.727018 | AR89: =+AH89/11 -> 81.181818 | AS89: =+AR89-AQ89 -> 0.4548001 | AT89: =+AH89/AQ89 -> 11.061972 | AU89: Ricardo Cardona | AV89: Lorena Cabrera | AY89: 1
A90: 89 | B90: Ignacio Ceroni | C90: 3007 | D90: 14 | E90: 12/03 al 31/03/2026 | F90: 46093 | G90: 46112 | J90: Montevideo | K90: Propio | M90: =+N90-H90 -> 2300 | N90: 2300 | O90: 9 | Q90: =+P90+O90 -> 9 | R90: =(N90/Q90) -> 255.55556 | S90: =(('Costo por negocio'!$B$3-DATA!R90)*DATA!O90)+('Costo por negocio'!$C$3-DATA!R90)*DATA!P90 -> 40 | T90: 46105 | U90: SI | V90: SI | W90: SI | Y90: SCG 4199 | Z90: 46105
A91: 90 | B91: Lucia Santamaría | C91: 3065 | D91: 2 | E91: 19/03 al 20/03/2026 | F91: 46100 | G91: 46101 | I91: 10 | J91: Montevideo | K91: Alquiler | M91: =+N91-H91 -> 1878.33 | N91: 1878.33 | O91: =19+5 -> 24 | Q91: =+P91+O91 -> 24 | R91: =(N91/Q91) -> 78.26375 | S91: =(('Costo por negocio'!$B$3-DATA!R91)*DATA!O91)+('Costo por negocio'!$C$3-DATA!R91)*DATA!P91 -> 4361.67 | T91: 46106 | U91: SI | V91: SI | W91: SI | Y91: ABD 6876 | Z91: 46106 | AA91: 96724 | AC91: 134 | AD91: 72951 | AE91: 46100.409 | AF91: 73199 | AG91: 46102.397 | AH91: =+AF91-AD91 -> 248 | AI91: 2 | AJ91: =+AI91*5 -> 10 | AK91: =+Q91-AJ91 -> 14 | AM91: =+AH91/Q91 -> 10.333333 | AN91: =+Q91/AI91 -> 12 | AQ91: =+N91/78.54 -> 23.915584 | AR91: =+AH91/11 -> 22.545455 | AS91: =+AR91-AQ91 -> -1.3701299 | AT91: =+AH91/AQ91 -> 10.369807
A92: 91 | B92: Claudia Parrilla | C92: 2005 | D92: 2 | E92: 31/03 al 01/04/2026 | F92: 46112 | G92: 46113 | H92: =20*387 -> 7740 | I92: 15 | J92: Montevideo, Colonia | K92: Alquiler | M92: =+N92-H92 -> -4782 | N92: 2958 | O92: 7 | P92: 10 | Q92: =+P92+O92 -> 17 | R92: =(N92/Q92) -> 174 | S92: =(('Costo por negocio'!$B$4-DATA!R92)*DATA!O92)+('Costo por negocio'!$C$4-DATA!R92)*DATA!P92 -> 3128 | T92: 46118 | U92: SI | V92: SI | W92: SI | Y92: BEC 5483 | Z92: 46118 | AD92: 76813 | AE92: 46111.658 | AF92: 77437 | AG92: 46114.378 | AH92: =+AF92-AD92 -> 624 | AI92: 2 | AJ92: =+AI92*5 -> 10 | AK92: =+Q92-AJ92 -> 7 | AM92: =+AH92/Q92 -> 36.705882 | AN92: =+Q92/AI92 -> 8.5 | AQ92: =+N92/78.54 -> 37.662338 | AR92: =+AH92/11 -> 56.727273 | AS92: =+AR92-AQ92 -> 19.064935 | AT92: =+AH92/AQ92 -> 16.568276
A93: 92 | B93: Ignacio Ceroni | C93: 3007 | D93: 3 | E93: 30/03 al 01/04/2026 | F93: 46111 | G93: 46113 | H93: 3000 | I93: 15 | J93: Montevideo, Paysandú | K93: Alquiler | M93: =+N93-H93 -> 541 | N93: 3541 | O93: 15 | P93: 0 | Q93: =+P93+O93 -> 15 | R93: =(N93/Q93) -> 236.06667 | S93: =(('Costo por negocio'!$B$4-DATA!R93)*DATA!O93)+('Costo por negocio'!$C$4-DATA!R93)*DATA!P93 -> 629 | T93: 46118 | U93: SI | V93: SI | W93: SI | X93: Se autorizo uso de auto automatico por tema de Salud de Nacho usd 75 p/dia. | Y93: BEC 5188 | Z93: 46118 | AC93: 225 | AD93: 67699 | AE93: 46111.375 | AF93: 68453 | AG93: 46113.726 | AH93: =+AF93-AD93 -> 754 | AI93: 3 | AJ93: =+AI93*5 -> 15 | AK93: =+Q93-AJ93 -> 0 | AM93: =+AH93/Q93 -> 50.266667 | AN93: =+Q93/AI93 -> 5 | AQ93: =+N93/78.54 -> 45.085307 | AR93: =+AH93/11 -> 68.545455 | AS93: =+AR93-AQ93 -> 23.460148 | AT93: =+AH93/AQ93 -> 16.723852
A94: 93 | B94: Gabriela Falero | C94: 2030 | D94: 3 | E94: 24/03 al 26/03/2026 | F94: 46105 | G94: 46107 | I94: 15 | J94: Montevideo, Canelones | K94: Alquiler | M94: =+N94-H94 -> 3458 | N94: 3458 | O94: 15 | Q94: =+P94+O94 -> 15 | R94: =(N94/Q94) -> 230.53333 | S94: =(('Costo por negocio'!$B$3-DATA!R94)*DATA!O94)+('Costo por negocio'!$C$3-DATA!R94)*DATA!P94 -> 442 | T94: 46111 | U94: SI | V94: SI | W94: SI | Y94: BEB 8417 | Z94: 46111 | AA94: 96757 | AC94: 74 | AD94: 128051 | AE94: 46106.378 | AF94: 128754 | AG94: 46108.378 | AH94: =+AF94-AD94 -> 703 | AI94: 3 | AJ94: =+AI94*5 -> 15 | AK94: =+Q94-AJ94 -> 0 | AM94: =+AH94/Q94 -> 46.866667 | AN94: =+Q94/AI94 -> 5 | AQ94: =+N94/78.54 -> 44.02852 | AR94: =+AH94/11 -> 63.909091 | AS94: =+AR94-AQ94 -> 19.88057 | AT94: =+AH94/AQ94 -> 15.966923 | AU94: Sylvia Antunez | AY94: 1
A95: 94 | B95: Fernando López | C95: 3117 | D95: 14 | E95: 12/03 al 31/03/2026 | F95: 46093 | G95: 46112 | J95: Montevideo | K95: Propio | M95: =+N95-H95 -> 3700 | N95: =2000+1700 -> 3700 | O95: 12 | Q95: =+P95+O95 -> 12 | R95: =(N95/Q95) -> 308.33333 | S95: =(('Costo por negocio'!$B$3-DATA!R95)*DATA!O95)+('Costo por negocio'!$C$3-DATA!R95)*DATA!P95 -> -580 | T95: 46112 | U95: SI | V95: SI | W95: SI | Y95: SCL 8868 | Z95: 46112
A96: 95 | B96: Lucia Santamaría | C96: 3065 | D96: 2 | E96: 25/03 al 26/03/2026 | F96: 46106 | G96: 46107 | I96: 10 | J96: Montevideo | K96: Alquiler | M96: =+N96-H96 -> 2611 | N96: 2611 | O96: =20+1 -> 21 | Q96: =+P96+O96 -> 21 | R96: =(N96/Q96) -> 124.33333 | S96: =(('Costo por negocio'!$B$3-DATA!R96)*DATA!O96)+('Costo por negocio'!$C$3-DATA!R96)*DATA!P96 -> 2849 | T96: 46112 | U96: SI | V96: SI | W96: SI | X96: Lucia tuvo un accidente en su auto propio que es automatico. Se autorizo uso de auto de alquiler automatico donde el costo es de usd 75 iva incluido por dia. Se estima que la reparación de su auto demore en el entorno a 1 mes. | Y96: ABD 6867 | Z96: 46112 | AA96: 96759 | AC96: 150 | AD96: 79305 | AE96: 46106.375 | AF96: 79541 | AG96: 46108.382 | AH96: =+AF96-AD96 -> 236 | AI96: 2 | AJ96: =+AI96*5 -> 10 | AK96: =+Q96-AJ96 -> 11 | AM96: =+AH96/Q96 -> 11.238095 | AN96: =+Q96/AI96 -> 10.5 | AQ96: =+N96/78.54 -> 33.244207 | AR96: =+AH96/11 -> 21.454545 | AS96: =+AR96-AQ96 -> -11.789661 | AT96: =+AH96/AQ96 -> 7.0989812
A97: 96 | B97: Ignacio Ceroni | C97: 3007 | D97: 2 | E97: 07/04 al 08/04/2026 | F97: 46119 | G97: 46120 | H97: 3000 | I97: 10 | J97: Montevideo, Paysandú | K97: Alquiler | M97: =+N97-H97 -> -859 | N97: 2141 | O97: 28 | Q97: =+P97+O97 -> 28 | R97: =(N97/Q97) -> 76.464286 | S97: =(('Costo por negocio'!$B$4-DATA!R97)*DATA!O97)+('Costo por negocio'!$C$4-DATA!R97)*DATA!P97 -> 5643 | T97: 46122 | U97: SI | V97: SI | W97: SI | Y97: BEB 4228 | Z97: 46122 | AD97: 96392 | AE97: 46119.449 | AF97: 96563 | AG97: 46121.44 | AH97: =+AF97-AD97 -> 171 | AI97: 2 | AJ97: =+AI97*5 -> 10 | AK97: =+Q97-AJ97 -> 18 | AM97: =+AH97/Q97 -> 6.1071429 | AN97: =+Q97/AI97 -> 14 | AQ97: =+N97/82.27 -> 26.024067 | AR97: =+AH97/11 -> 15.545455 | AS97: =+AR97-AQ97 -> -10.478613 | AT97: =+AH97/AQ97 -> 6.5708407
A98: 97 | B98: Luis Amicone | C98: 3075 | D98: 3 | E98: 07/04 al 09/04/2026 | F98: 46119 | G98: 46121 | H98: 7000 | I98: 15 | J98: Montevideo, Tacuarembo | K98: Alquiler | M98: =+N98-H98 -> -1217 | N98: =1425+2810+1548 -> 5783 | P98: =20+7 -> 27 | Q98: =+P98+O98 -> 27 | R98: =(N98/Q98) -> 214.18519 | S98: =(('Costo por negocio'!$B$4-DATA!R98)*DATA!O98)+('Costo por negocio'!$C$4-DATA!R98)*DATA!P98 -> 5395 | T98: 46122 | U98: SI | V98: SI | W98: SI | Y98: BEC 5630 | Z98: 46122 | AD98: 73468 | AE98: 46118.708 | AF98: 74465 | AG98: 46121.651 | AH98: =+AF98-AD98 -> 997 | AI98: 3 | AJ98: =+AI98*5 -> 15 | AK98: =+Q98-AJ98 -> 12 | AM98: =+AH98/Q98 -> 36.925926 | AN98: =+Q98/AI98 -> 9 | AQ98: =+N98/82.27 -> 70.292938 | AR98: =+AH98/11 -> 90.636364 | AS98: =+AR98-AQ98 -> 20.343426 | AT98: =+AH98/AQ98 -> 14.183502
A99: 98 | B99: Claudia Parrilla | C99: 2005 | D99: 3 | E99: 07/04 al 09/04/2026 | F99: 46119 | G99: 46121 | H99: =20*260 -> 5200 | I99: 15 | J99: Montevideo, Canelones, San José | K99: Alquiler | M99: =+N99-H99 -> -2118 | N99: 3082 | O99: 5 | P99: 15 | Q99: =+P99+O99 -> 20 | R99: =(N99/Q99) -> 154.1 | S99: =(('Costo por negocio'!$B$4-DATA!R99)*DATA!O99)+('Costo por negocio'!$C$4-DATA!R99)*DATA!P99 -> 4518 | T99: 46122 | U99: SI | V99: SI | W99: SI | Y99: BEE 0823 | Z99: 46122 | AD99: 10338 | AE99: 46119.385 | AF99: 10917 | AG99: 46122.375 | AH99: =+AF99-AD99 -> 579 | AI99: 3 | AJ99: =+AI99*5 -> 15 | AK99: =+Q99-AJ99 -> 5 | AM99: =+AH99/Q99 -> 28.95 | AN99: =+Q99/AI99 -> 6.6666667 | AQ99: =+N99/82.27 -> 37.462015 | AR99: =+AH99/11 -> 52.636364 | AS99: =+AR99-AQ99 -> 15.174348 | AT99: =+AH99/AQ99 -> 15.455655
A100: 99 | B100: Lorena Cabrera | C100: 1618 | D100: 3 | E100: 07/04 al 09/04/2026 | F100: 46119 | G100: 46121 | H100: 3500 | I100: 15 | J100: Canelones, Maldonado | K100: Alquiler | M100: =+N100-H100 -> 674.8 | N100: 4174.8 | O100: 10 | Q100: =+P100+O100 -> 10 | R100: =(N100/Q100) -> 417.48 | S100: =(('Costo por negocio'!$B$4-DATA!R100)*DATA!O100)+('Costo por negocio'!$C$4-DATA!R100)*DATA!P100 -> -1394.8 | T100: 46126 | U100: SI | V100: SI | W100: SI | Y100: BED 8126 | Z100: 46126 | AD100: 124847 | AE100: 46118.708 | AF100: 125677 | AG100: 46122.396 | AH100: =+AF100-AD100 -> 830 | AI100: 3 | AJ100: =+AI100*5 -> 15 | AK100: =+Q100-AJ100 -> -5 | AM100: =+AH100/Q100 -> 83 | AN100: =+Q100/AI100 -> 3.3333333 | AQ100: =+N100/82.27 -> 50.745108 | AR100: =+AH100/11 -> 75.454545 | AS100: =+AR100-AQ100 -> 24.709438 | AT100: =+AH100/AQ100 -> 16.356257
...

Sheet Costo por negocio
A1: Mes | B1: Menos de 100KM | C1: Más de 100KM
A2: 46023 | B2: 263 | C2: 392
A3: 46082 | B3: 260 | C3: 387
A4: 46113 | B4: 278 | C4: 414
A5: 46143 | B5: 297 | C5: 443
A12: Costo máximo por Negocio Actual: | B12: =B5 -> 297 | C12: =C5 -> 443

Sheet Costo Combustible
A1: AJUSTES DE PRECIOS DE COMBUSTIBLES DESDE 01/05/2026
B2: Precio Nafta
A3: Concepto | B3: 46113 | C3: 46143 | D3: Diferencia $ | E3: Variación %
D4: Abril 2026 a Mayo 2026 | E4: Abril 2026 a Mayo 2026
A5: Nafta super | B5: 82.27 | C5: 88.03 | D5: =+C5-B5 -> 5.76 | E5: =+D5/B5 -> 0.070013371
A6: Menos 100 km. | B6: 277.96888 | C6: =B6+(B6*E5) -> 297.43042 | D6: =+C6-B6 -> 19.461538 | E6: =+D6/B6 -> 0.070013371
A7: Más 100 km. | B7: 414.2066 | C7: =B7+(B7*E6) -> 443.2066 | D7: =+C7-B7 -> 29 | E7: =+D7/B7 -> 0.070013371
